{
  "ARCRD": "ARCRD-里瓦达维亚/里瓦达维亚海军准将城(Comodoro Rivadavia)",
  "ARH": "ARH-Arkhangelsk",
  "ARMDQ": "ARMDQ-马德普拉塔(Mar del Plata)",
  "ARPMY": "ARPMY-马德林港(Puerto Madryn)",
  "ARQQN": "ARQQN-克肯/库库恩(Quequen)",
  "ARROS": "ARROS-罗萨里奥(Rosario)",
  "ARSNS": "ARSNS-圣尼古拉斯(San Nicolas de los Arroyos)",
  "JPTOS": "JPTOS-富山新港(TOYAMA SHINKO)",
  "AUKWI": "AUKWI-克维纳纳(KWINANA)",
  "DOCAU": "DOCAU-考赛多港(CAUCEDO)",
  "MZUEL": "MZUEL-克利马内(QUELIMANE)",
  "JPYAW": "JPYAW-八幡(YAWATA)",
  "IDCID": "IDCID-契万丹(CIWANDAN)",
  "IDBNA": "IDBNA-邦盖(BUNTA)",
  "IDBTA": "IDBTA-巴图阿帕(BATU AMPAR)",
  "MXAVD": "MXAVD-阿尔瓦拉多(Alvarado)",
  "FIHEL": "FIHEL-赫尔辛基(Helsinki (Helsingfors))",
  "FIHMN": "FIHMN-哈米纳(Hamina (Fredrikshamn))",
  "FIKOK": "FIKOK-科科拉(Kokkola (Karleby))",
  "FIKRS": "FIKRS-克里斯提南考蓬基(Kristiinankaupunki (Kristinestad))",
  "FIOLU": "FIOLU-奥鲁/奥卢(Oulu)",
  "FIRAU": "FIRAU-劳马(Rauma (Raumo))",
  "FITOR": "FITOR-托尔尼奥/托尔尼欧(Tornio (Tornea))",
  "CNTGG": "CNTGG-塘沽(Tanggu)",
  "CNTGS": "CNTGS-唐山(Tangshan)",
  "CNTOJ": "CNTOJ-同江(Tongjiang)",
  "CNTOL": "CNTOL-铜陵(Tongling)",
  "CNTPW": "CNTPW-太平湾(Taipingwan)",
  "CNTZU": "CNTZU-泰州(Taizhou)",
  "CNWAS": "CNWAS-万山(Wanshan)",
  "CNWAZ": "CNWAZ-湾仔(Wanzai)",
  "CNWEI": "CNWEI-威海港(Weihaigang)",
  "CNWHG": "CNWHG-武汉港(Wuhangang)",
  "CNWHI": "CNWHI-芜湖(Wuhu)",
  "CNWIG": "CNWIG-外港(Waigang)",
  "CNWIH": "CNWIH-外海(Waihai)",
  "CNWIT": "CNWIT-围头(Weitou)",
  "CNWUK": "CNWUK-乌坎(Wukan)",
  "CNWUZ": "CNWUZ-梧州(Wuzhou)",
  "CNWZH": "CNWZH-万州(Wanzhou)",
  "CNXAM": "CNXAM-厦门",
  "CNXAO": "CNXAO-小榄(Xiaolan)",
  "CNXCU": "CNXCU-肖厝(Xiaocuo)",
  "CNXHH": "CNXHH-新会河口(Xinhuihekou)",
  "CNXIN": "CNXIN-新会(Xinhui)",
  "CNXSP": "CNXSP-象山石浦(Xiangshanshipu)",
  "CNXTI": "CNXTI-西堤(Xidi)",
  "CNXTO": "CNXTO-溪头(Xitou)",
  "CNXYG": "CNXYG-秀屿(Xiuyu)",
  "CNXZI": "CNXZI-祥芝(Xiangzhi)",
  "CNYIK": "CNYIK-营口",
  "CNYJI": "CNYJI-阳江(Yangjiang)",
  "CNYTA": "CNYTA-烟台(Yantai)",
  "CNYTN": "CNYTN-盐田(Yantian)",
  "CNZGW": "CNZGW-漳湾(Zhangwan)",
  "CNZJG": "CNZJG-张家港(Zhangjiagang)",
  "CNZPO": "CNZPO-闸坡(Zhapo)",
  "CNZSN": "CNZSN-中山(Zhongshan)",
  "CNZZU": "CNZZU-漳州(Zhangzhou)",
  "COCTG": "COCTG-卡塔赫纳(Cartagena)",
  "COTCO": "COTCO-图马科(Tumaco)",
  "CRCAL": "CRCAL-卡尔德拉(Caldera)",
  "CRLIO": "CRLIO-利蒙/利蒙港(Puerto Limon)",
  "CUCAR": "CUCAR-卡德纳斯(Cardenas)",
  "CUSCU": "CUSCU-圣地亚哥(Santiago de Cuba)",
  "CVMIN": "CVMIN-明德卢/明德卢港(Mindelo)",
  "CYLMS": "CYLMS-利马索尔(Limassol)",
  "DEBRE": "DEBRE-不来梅(Bremen)",
  "DECUX": "DECUX-库克斯港(Cuxhaven)",
  "DEHAM": "DEHAM-汉堡(Hamburg)",
  "DELBC": "DELBC-吕贝克(Lubeck)",
  "DKAAL": "DKAAL-奥尔堡(Aalborg)",
  "AEAUH": "AEAUH-阿布扎比(Abu Dhabi)",
  "AEFJR": "AEFJR-富查伊拉(Fujairah/ Al Fujayrah)",
  "YEADE": "YEADE-亚丁(Aden)",
  "YEHOD": "YEHOD-荷台达(Hodeidah)",
  "YEMOK": "YEMOK-穆哈(Mokha)",
  "YESAL": "YESAL-萨利夫(Saleef/Salif/Saleef Port)",
  "YTDZA": "YTDZA-藻德济(Dzaoudzi)",
  "ZACPT": "ZACPT-开普敦(Cape Town)",
  "ZADUR": "ZADUR-德班(Durban)",
  "ZAELS": "ZAELS-东伦敦(East London)",
  "ZAMZY": "ZAMZY-莫塞尔贝/莫塞尔港(Mossel Bay)",
  "ZAPLZ": "ZAPLZ-伊丽莎白港(Port Elizabeth)",
  "ZARCB": "ZARCB-里查德湾/里查兹贝(Richards Bay)",
  "HRPUY": "HRPUY-普拉(Pula)",
  "HRRJK": "HRRJK-里耶卡(Rijeka)",
  "HTACA": "HTACA-莱凯(Les Cayes)",
  "HTCAP": "HTCAP-海地角(Cap-Haitien)",
  "HTGVS": "HTGVS-戈纳伊夫/利贝特堡(Gonaives)",
  "HTPAP": "HTPAP-太子港(Port-au-Prince)",
  "USBOS": "USBOS-波士顿(Boston)",
  "USCDE": "USCDE-Camden",
  "USCLE": "USCLE-克利夫兰(Cleveland)",
  "USDET": "USDET-底特律(Detroit)",
  "USHNL": "USHNL-火奴鲁鲁(Honolulu)",
  "USHVN": "USHVN-纽黑文(New Haven)",
  "USJVL": "USJVL-杰克逊维尔(Janesville)",
  "USLCH": "USLCH-莱克查尔斯(Lake Charles)",
  "USMIA": "USMIA-迈阿密(Miami)",
  "USNYC": "USNYC-纽约(New York)",
  "USPDX": "USPDX-波特兰(Portland)",
  "USSAV": "USSAV-萨凡纳(Savannah)",
  "USSEA": "USSEA-西雅图(Seattle)",
  "USSFO": "USSFO-旧金山/圣弗朗西斯科(San Francisco)",
  "USTIW": "USTIW-塔科马(Tacoma)",
  "USTPA": "USTPA-坦帕(Tampa)",
  "USWTN": "USWTN-威尔明顿(Wilmington)",
  "UTN": "UTN-Municipal",
  "UYNVP": "UYNVP-新帕尔米拉(Nueva Palmira)",
  "VECUM": "VECUM-库马纳(Cumana)",
  "VEGUI": "VEGUI-圭里亚(Guiria)",
  "VEPBL": "VEPBL-卡贝略港(Puerto Cabello)",
  "VEPCZ": "VEPCZ-拉克鲁斯港/克鲁斯港(Puerto La Cruz)",
  "VEPZO": "VEPZO-奥尔达斯港/奥达斯港(Puerto Ordaz)",
  "VEY": "VEY-Vestmannaeyjar",
  "VGRAD": "VGRAD-罗德城(Road Town, Tortola)",
  "VICHA": "VICHA-夏洛特阿马利亚(Charlotte Amalie, St Thomas)",
  "VNDAD": "VNDAD-岘港(Da-Nang/ Da Nang)",
  "VNHPH": "VNHPH-海防(Haiphong)",
  "VNNHA": "VNNHA-芽庄(Nha Trang)",
  "VNUIH": "VNUIH-归仁(Qui Nhon)",
  "IDANR": "IDANR-安亚(ANYER)",
  "TRAMB": "TRAMB-阿姆巴利(AMBARLI)",
  "AERUW": "AERUW-鲁韦斯(AR RUWAYS)",
  "USLBN": "USLBN-黎巴嫩(LEBANON)",
  "ISKEV": "ISKEV-凯夫拉维克(Keflavikurkaupstadur)",
  "ISP": "ISP-Long Island-Macarthur Airport",
  "ISVES": "ISVES-韦斯特曼纳岛/维斯特曼纳加(Vestmannaeyjar - hofn)",
  "ITBLT": "ITBLT-巴列塔(Barletta)",
  "ITCAG": "ITCAG-卡利亚里/卡利阿里(Cagliari)",
  "ITGAE": "ITGAE-加埃塔(Gaeta)",
  "ITGOA": "ITGOA-热那亚(Genoa)",
  "ITLIV": "ITLIV-里窝那(Livorno/ Leghorn)",
  "ITMLZ": "ITMLZ-米拉佐(Milazzo)",
  "ITRAN": "ITRAN-腊万纳(Ravenna)",
  "ITTAR": "ITTAR-塔兰托(Taranto)",
  "ITVCE": "ITVCE-威尼斯(Venezia/ Venice)",
  "AUPWL": "AUPWL-沃尔特",
  "IDPUM": "IDPUM-波马拉",
  "INPAN": "INPAN-帕纳吉",
  "MYLDU": "MYLDU-lahad datu",
  "RUNIA": "RUNIA-NIKOLAYEVSK-NA-AMURE",
  "RUSOG": "RUSOG-索维斯卡亚戈万",
  "CNLGY": "CNLGY-龙眼",
  "AUHPT": "AUHPT-海角",
  "PESNX": "PESNX-圣尼古拉斯",
  "IDIBT": "IDIBT-INDONESIA BULK TERMINAL",
  "AUDIT": "AUDIT-Dalrymple islet  达尔林普尔岛",
  "RUIKS": "RUIKS-季克西",
  "IDBTN": "IDBTN-巴淡",
  "JPMOJ": "JPMOJ-MOJI门司",
  "ATJOA": "ATJOA-圣约翰港",
  "CLCCH": "CLCCH-CHILE CHICO",
  "USCOB": "USCOB-COOS BAY 库斯湾",
  "JPSMT": "JPSMT-下津",
  "PGNPG": "PGNPG-尼帕",
  "SARAR": "SARAR-拉斯海夫吉",
  "EESIL": "EESIL-锡拉迈埃",
  "CNQGD": "CNQGD-青岛前湾非保税港",
  "KRWAD": "KRWAD-WANDO莞岛",
  "CNLXA": "CNLXA-拉萨贡嘎国际机场",
  "USWWO": "USWWO-韦斯特维格",
  "CNQWG": "CNQWG-青岛前湾保税港",
  "JPHSM": "JPHSM-Hososhima细岛",
  "CNFQX": "CNFQX-福清下垄",
  "CNGZG": "CNGZG-广州港",
  "KPGON": "KPGON-松林",
  "BMFPT": "BMFPT-弗里波特",
  "JPNAN": "JPNAN-NAKANOSEKI",
  "JPWAM": "JPWAM-WAKAMATSU　若松",
  "PHSNG": "PHSNG-SANGI CEBU三基",
  "USZD8": "USZD8-INDIAN HARBOUR",
  "JPKRE": "JPKRE-吴市",
  "VEJOT": "VEJOT-JOSE TERMINAL",
  "KRPTK": "KRPTK-平泽",
  "PGLUS": "PGLUS-Luise Harbour",
  "PAPAC": "PAPAC-巴拿马城",
  "JPETA": "JPETA-TEAJIMA",
  "IDDAS": "IDDAS-达博",
  "JPSBS": "JPSBS-SHIBUSHI",
  "JPKGA": "JPKGA-KAKOGAWA  加古川",
  "AOGPO": "AOGPO-普鲁托尼GREATER PLUTO",
  "FIPIE": "FIPIE-PIETARSAARI",
  "MNULB": "MNULB-乌兰巴托",
  "JPSMN": "JPSMN-境港",
  "USGFP": "USGFP-GULF PORT",
  "JPHIC": "JPHIC-HITACHINAKA",
  "JPONO": "JPONO-尾道",
  "KRTYG": "KRTYG-统营",
  "SBNOR": "SBNOR-诺罗",
  "ETADS": "ETADS-亚的斯亚贝巴",
  "DWC": "DWC-迪拜世界中央国际机场",
  "AOMAL": "AOMAL-马隆格",
  "INBED": "INBED-贝迪",
  "CNLSN": "CNLSN-岚山１",
  "KPKAB": "KPKAB-三甲屯门港",
  "JPMYJ": "JPMYJ-松山",
  "USOLM": "USOLM-奥林匹亚",
  "CNQDP": "CNQDP-青岛港",
  "IDBLU": "IDBLU-朋古鲁",
  "KRGHY": "KRGHY-GOHYEON高砚",
  "JPMKO": "JPMKO-宫口",
  "USZKN": "USZKN-波德申",
  "IDTBA": "IDTBA-TANJUNG BARA",
  "IDKIJ": "IDKIJ-基姜",
  "IDSUL": "IDSUL-苏拉和",
  "KPSII": "KPSII-新义州",
  "CORCO": "CORCO-里奥科尔多瓦",
  "CAKIN": "CAKIN-金斯顿",
  "VNCMY": "VNCMY-清迈",
  "RUOLB": "RUOLB-奥尔加",
  "BRGIB": "BRGIB-PORT OF GUAIBA瓜伊巴",
  "WLG": "WLG-惠灵顿国际机场",
  "KRCHA": "KRCHA-济州",
  "IDKUM": "IDKUM-库买",
  "USRIC": "USRIC-里士满",
  "CLCNL": "CLCNL-科罗内尔",
  "CNSAM": "CNSAM-荣成市三星重工业码头",
  "THS": "THS-公海the high seas",
  "JPMII": "JPMII-MIIKE三池",
  "IRBAH": "IRBAH-阿萨泸耶赫",
  "PGOPB": "PGOPB-OPEN BAY",
  "CAPNO": "CAPNO-POINTE NOIRE 黑角",
  "KNCHS": "KNCHS-查尔斯顿",
  "JPSAG": "JPSAG-佐贺关",
  "RUDKS": "RUDKS-DIKSON 迪克森",
  "JPYAT": "JPYAT-八代",
  "AUGOV": "AUGOV-GOVE",
  "AEZUR": "AEZUR-ZIKKU ISLAND",
  "JPIZA": "JPIZA-严原",
  "VNBNO": "VNBNO-巴高伊",
  "KRHSD": "KRHSD-黑山岛",
  "BEANT": "BEANT-ANTWERP",
  "BZBMP": "BZBMP-贝尔莫潘",
  "RUPTN": "RUPTN-普利斯坦",
  "CNWCG": "CNWCG-吴川港",
  "USDOU": "USDOU-道格拉斯",
  "TWMLI": "TWMLI-马里奥",
  "AOSOY": "AOSOY-SOYO",
  "USKAM": "USKAM-卡拉马",
  "AUABP": "AUABP-阿博特波特",
  "PHJPM": "PHJPM-JOSE PANGANIBAN",
  "JPKOK": "JPKOK-KOKURA",
  "IDKNL": "IDKNL-考隆诺达尔",
  "BRPOU": "BRPOU-PONTA UBU",
  "AULAT": "AULAT-拉塔",
  "JPFUK": "JPFUK-福冈(Fukuoka)",
  "JPHKD": "JPHKD-函馆(Hakodate)",
  "JPKKJ": "JPKKJ-北九州(Kitakyushu)",
  "JPMUR": "JPMUR-室兰(Muroran)",
  "JPOIT": "JPOIT-大分(Oita)",
  "JPONA": "JPONA-小名滨(Onahama)",
  "JPSSB": "JPSSB-佐世保(Sasebo)",
  "JPTRG": "JPTRG-敦贺(Tsuruga)",
  "JPWAK": "JPWAK-和歌山(Wakayama)",
  "JMOCJ": "JMOCJ-奥乔里奥斯湾/奥科里奥斯(Ocho Rios)",
  "KPHGM": "KPHGM-兴南(Hungnam)",
  "KPSIN": "KPSIN-新浦(Sinpo)",
  "KRMAS": "KRMAS-马山(Masan)",
  "KRMUK": "KRMUK-墨湖(Mukho/Donghae)",
  "KRYOS": "KRYOS-丽水(Yosu/ Yeosu)",
  "ARZAE": "ARZAE-萨拉特(ZARATE)",
  "PHSFS": "PHSFS-苏比克(SUBIC BAY)",
  "PHTAC": "PHTAC-塔克洛班(TACLOBAN)",
  "JPIRI": "JPIRI-伊万里(IMARI)",
  "CNRUG": "CNRUG-如皋港",
  "LBKYE": "LBKYE-的黎波里(Tripoli)",
  "LBSAY": "LBSAY-西顿/赛达(Sidon/Saida/ Sayda)",
  "LKGAL": "LKGAL-加勒(Galle)",
  "LKKNK": "LKKNK-坎凯桑图赖(Kankesanturai)",
  "LKTRR": "LKTRR-亭可马里(Trincomalee)",
  "DKCPH": "DKCPH-哥本哈根(Kobenhavn/Copenhagen)",
  "PTADH": "PTADH-英雄港(Angra do Heroismo)",
  "PRLAM": "PRLAM-瓜亚马/拉斯马雷亚斯(Las Mareas (Guayama))",
  "PRPSE": "PRPSE-蓬塞(Ponce)",
  "PTLIS": "PTLIS-里斯本(Lisboa)",
  "PTOPO": "PTOPO-波尔图(Porto)",
  "PTPRM": "PTPRM-波尔蒂芒(Portimao)",
  "PTSET": "PTSET-塞图巴尔/西图巴尔(Setubal)",
  "PWROR": "PWROR-科罗尔/格罗尔(Koror)",
  "QADOH": "QADOH-多哈(Doha)",
  "AUHAS": "AUHAS-海斯廷斯(HASTINGS)",
  "USKVL": "USKVL-凯瓦利纳(KIVALINA)",
  "TRALI": "TRALI-阿利亚加(ALIAGA)",
  "CNBLN": "CNBLN-北仑港(BEILUN)",
  "BRNVT": "BRNVT-纳维根特斯(NAVEGANTSE)",
  "JPNAI": "JPNAI-直岛(NAOSHIMA ISLAND)",
  "ARSLO": "ARSLO-圣洛伦索(SAN LORENZO)",
  "JPSAK": "JPSAK-界港(SAKAI)",
  "NGONN": "NGONN-奥纳港(ONNE)",
  "DEMAL": "DEMAL-马尔(MARL)",
  "VEPLA": "VEPLA-帕卢瓦(PALUA)",
  "MUJOH": "MUJOH-柔佛(JOHOR)",
  "JPSNB": "JPSNB-仙北(SENBOKU)",
  "CABCO": "CABCO-贝科莫(BATE COMEAU)",
  "MGTNR": "MGTNR-安塔那那利佛(ANTANANARIVO)",
  "IDTJB": "IDTJB-丹戎巴莱(TANJUNG BALAIKARIMUM)",
  "JPKOC": "JPKOC-高知(KOCHZ)",
  "INPAV": "INPAV-皮帕瓦沃(PIPAVAV)",
  "ZRH": "ZRH-苏黎世国际机场",
  "PCMAJ": "PCMAJ-马绍尔群岛(Majuro)",
  "GBBAC": "GBBAC-北爱尔兰(NORTHERN IRELAND)",
  "AUPWA": "AUPWA-沃尔科特港(PORT WALCOTT)",
  "CLHPO": "CLHPO-huachipato",
  "USRCD": "USRCD-里士满(RICHMOND(VA.))",
  "IDBON": "IDBON-邦坦(BONTANG)",
  "TSE": "TSE-阿斯塔纳机场",
  "CNTSI": "CNTSI-靖江(JINGJIANG)",
  "AUEPR": "AUEPR-esperance",
  "USPAL": "USPAL-艾伦港(PORT ALLEN)",
  "PWMAH": "PWMAH-MALAKAL HARBOUR",
  "TRMAR": "TRMAR-marmara",
  "ZAZBA": "ZAZBA-库哈(COEGA)",
  "JPNMK": "JPNMK-波方(NAMIKATA)",
  "NYT": "NYT-内比都(Nay Pyi Taw)",
  "EEPLA": "EEPLA-帕尔迪斯基(PALDISKI)",
  "CANWE": "CANWE-新威斯敏斯特(NEW WESTMINSTER)",
  "KWSWK": "KWSWK-舒韦赫(SHUWAIKH)",
  "INENR": "INENR-印诺尔(ENNORE)",
  "KRSCP": "KRSCP-三千浦(SAMCHEONPO)",
  "AEPRA": "AEPRA-拉希德港(Port Rashid)",
  "VNGOD": "VNGOD-古多(GODAU)",
  "TRGEB": "TRGEB-盖布泽(GEBZE)",
  "CNQID": "CNQID-启东港(Qidong)",
  "TTPTS": "TTPTS-利萨斯角(Point Lisas)",
  "AEJEA": "AEJEA-阿里山(Jebel Ali)",
  "IDANY": "IDANY-安雅尔(ANYER)",
  "AESHJ": "AESHJ-舍尔杰/沙迦(Sharjah)",
  "TQUQR": "TQUQR-务姆盖斯尔(UMM QASR)",
  "AEKLF": "AEKLF-豪尔费坎(Khor Fakkan/ Khor al Fakkan)",
  "DEBZL": "DEBZL-巴塞尔(basel)",
  "JPOMZ": "JPOMZ-御前崎(OMAEZAKI)",
  "VNPMY": "VNPMY-浮美(PHU MY)",
  "IDLUG": "IDLUG-卢布(LUBUK GAUNG)",
  "VNVUA": "VNVUA-万安港(VUNG ANG PORT)",
  "USCOC": "USCOC-科珀斯克里斯蒂(CORPUS CHRISTI)",
  "VNSDN": "VNSDN-山阳(SON DUONG)",
  "BRITQ": "BRITQ-伊塔基(ITAQUI)",
  "CZX": "CZX-常州奔牛国际机场(Changzhoubennuijichang)",
  "CNGUO": "CNGUO-国电码头(Guodian)",
  "CNYUA": "CNYUA-元洪码头(Yuanhong)",
  "UATHE": "UATHE-费奥多西亚(THEODOSIA)",
  "USPTS": "USPTS-匹兹堡(PITTSBURG)",
  "IDSOR": "IDSOR-苏朗(SORONG)",
  "CNJOG": "CNJOG-景洪(Jinghong)",
  "MMSLG": "MMSLG-索累港(SUOLEI)",
  "MMWBG": "MMWBG-万泵港(WANGBENG)",
  "LAMMG": "LAMMG-孟莫港(MENGMO)",
  "LAHSG": "LAHSG-会赛港(HUISAI)",
  "ALDRZ": "ALDRZ-都拉斯(Durres/ Durazzo)",
  "ANWIL": "ANWIL-威廉斯塔德(Willemstad)",
  "AOBUG": "AOBUG-本格拉(Benguela)",
  "ANKRA": "ANKRA-克拉伦代克(Kralendijk)",
  "AOLOB": "AOLOB-洛比托(Lobito)",
  "ASPPG": "ASPPG-帕果帕果(Pago Pago)",
  "AOPBN": "AOPBN-安博因港/阿姆博姆港/昂博因港(Porto Amboim)",
  "ALSAR": "ALSAR-萨兰达(Sarande)",
  "ALVOA": "ALVOA-发罗拉(Vlone/Vlora/Valona)",
  "AUALH": "AUALH-奥尔巴尼(Albany)",
  "ARBHI": "ARBHI-布兰卡港(Bahia Blanca)",
  "ARBUE": "ARBUE-布宜诺斯艾利斯(Buenos Aires)",
  "ARCVI": "ARCVI-奥利维亚(Caleta Olivia)",
  "ARDME": "ARDME-迪亚曼泰/迪亚曼特/戴芒特(Diamante)",
  "AWSNL": "AWSNL-圣尼古拉斯湾(Sint Nicolaas)",
  "ARLPG": "ARLPG-拉普拉塔(La Plata)",
  "BBBGI": "BBBGI-布里奇敦(Bridgetown)",
  "ARNEC": "ARNEC-内科切阿(Necochea)",
  "ARPUD": "ARPUD-德塞阿多港(Puerto Deseado)",
  "ARRGL": "ARRGL-里奥加耶戈斯(Rio Gallegos)",
  "ARRZA": "ARRZA-圣克鲁斯(Santa Cruz)",
  "ARSSN": "ARSSN-圣塞瓦斯蒂安/圣塞瓦斯提安(San Sebastian)",
  "ARULA": "ARULA-圣胡利安(San Julian)",
  "ARVIAT": "Arviat-Arviat",
  "AUCNS": "AUCNS-凯恩斯(Cairns)",
  "AUDRW": "AUDRW-达尔文(Darwin)",
  "AUGEX": "AUGEX-吉朗(Geelong)",
  "AUH": "AUH-阿布扎比机场",
  "AUMEL": "AUMEL-墨尔本(Melbourne)",
  "AUPHE": "AUPHE-黑德兰港(Port Hedland)",
  "AUPUG": "AUPUG-奥古斯塔港(Port Augusta)",
  "AUWEI": "AUWEI-韦帕(Weipa)",
  "BDCGP": "BDCGP-吉大港(Chittagong)",
  "BDKHL": "BDKHL-库尔纳(Khulna)",
  "BDL": "BDL-Bradley International Airport",
  "BDMGL": "BDMGL-蒙拉(Mungla/ Mongla)",
  "BEGNE": "BEGNE-根特(Gent (Ghent))",
  "BJCOO": "BJCOO-科托努/科托诺(Cotonou)",
  "BGBOJ": "BGBOJ-布加斯(Bourgas/ Burgas)",
  "BJPTN": "BJPTN-波多诺伏(Porto-Novo)",
  "BGVAR": "BGVAR-瓦尔纳(Varna)",
  "BMSGE": "BMSGE-圣乔治(Saint George)",
  "BNMUA": "BNMUA-麻拉(Muara)",
  "BNSER": "BNSER-诗里亚(Seria)",
  "BRIOS": "BRIOS-伊列乌斯(Ilheus)",
  "BRIQI": "BRIQI-伊塔基(Itaqui)",
  "BRM": "BRM-Barquisimeto",
  "BRMCP": "BRMCP-马卡帕(Macapa)",
  "MXACA": "MXACA-阿卡普尔科(Acapulco)",
  "MXCPE": "MXCPE-坎佩切(Campeche)",
  "MXESE": "MXESE-恩塞纳达(Ensenada)",
  "MXLZC": "MXLZC-拉萨罗卡德纳斯(Lazaro Cardenas)",
  "MXMTT": "MXMTT-米纳蒂特兰/米纳提特兰(Minatitlan)",
  "MXSCX": "MXSCX-萨利纳克鲁斯(Salina Cruz)",
  "MXTAM": "MXTAM-坦皮科(Tampico)",
  "MXZ": "MXZ-梅县机场(Meixianjichang)",
  "MXZLO": "MXZLO-曼萨尼略(Manzanillo)",
  "MYBTU": "MYBTU-民都鲁(Bintulu)",
  "MYKCH": "MYKCH-古晋(Kuching)",
  "MYLBU": "MYLBU-纳闽(Labuan)",
  "MYMYY": "MYMYY-米里(Miri)",
  "MYPGU": "MYPGU-帕西古当(Pasir Gudang)",
  "MYTWU": "MYTWU-斗湖(Tawau)",
  "NGCBQ": "NGCBQ-卡拉巴尔(Calabar)",
  "NGLOS": "NGLOS-拉各斯(Lagos)",
  "NGORO": "NGORO-奥尼(Oron)",
  "MZMPM": "MZMPM-马普托(Maputo)",
  "MZPOL": "MZPOL-彭巴(Pemba)",
  "NAWVB": "NAWVB-鲸湾港/沃尔维斯港(Walvis Bay)",
  "NIBEF": "NIBEF-布卢菲尔兹(Bluefields)",
  "NISJS": "NISJS-南圣胡安(San Juan del Sur)",
  "NKG": "NKG-南京禄口国际机场(Nanjinglukouguojijichang)",
  "MZBEW": "MZBEW-贝拉(Beira)",
  "NLIJM": "NLIJM-艾默伊登/艾莫伊登(IJmuiden)",
  "NGAPP": "NGAPP-阿帕帕(Apapa)",
  "NLTNZ": "NLTNZ-泰尔讷曾(Terneuzen)",
  "NLZAA": "NLZAA-赞丹(Zaandam)",
  "NOAES": "NOAES-奥勒松(Alesund/Aalesund)",
  "NOBOO": "NOBOO-博多(Bodo)",
  "NOGTD": "NOGTD-格里姆斯塔(Grimstad)",
  "NOKRS": "NOKRS-克里斯蒂安桑(Kristiansand)",
  "NOMJF": "NOMJF-莫舍恩/莫绍恩(Mosjoen)",
  "NOMSS": "NOMSS-莫斯(Moss)",
  "NOOSL": "NOOSL-奥斯陆(Oslo)",
  "NOTRD": "NOTRD-特隆赫姆(Trondheim)",
  "GTSNJ": "GTSNJ-圣何塞(San Jose)",
  "GUAGA": "GUAGA-阿加尼亚(Agana)",
  "GUAPR": "GUAPR-阿普拉(Apra (Agana))",
  "GRVOL": "GRVOL-伏洛斯/沃勒斯(Volos)",
  "GTPBR": "GTPBR-巴里奥斯港(Puerto Barrios)",
  "GUGUM": "GUGUM-Guam",
  "NZLYT": "NZLYT-利特尔顿(Lyttelton)",
  "NZNPE": "NZNPE-内皮尔/纳皮尔(Napier)",
  "NZORR": "NZORR-奥塔戈(Otago Harbour)",
  "GWBOL": "GWBOL-博拉多(Bolama)",
  "GWCAC": "GWCAC-卡谢马(Cacheu)",
  "HNPCR": "HNPCR-科尔特斯港(Puerto Cortes)",
  "GWOXB": "GWOXB-比绍(Bissau)",
  "GWT": "GWT-Westerland",
  "GXQ": "GXQ-Teniente Vidal",
  "GYGEO": "GYGEO-乔治敦/乔治顿(Georgetown)",
  "CNDLC": "CNDLC-大连港",
  "AESHR": "AESHR-席赫尔(ASH SHIHR)",
  "INHDA": "INHDA-哈迪亚(HALDIA)",
  "JPTHS": "JPTHS-丰桥(TOYOHASHI)",
  "AOPLN": "AOPLN-普罗托尼(PLUTONIO)",
  "IRBAY": "IRBAY-阿萨鲁耶(ASSALUYEH)",
  "IDSPT": "IDSPT-桑皮特(SAMPIT)",
  "MYKER": "MYKER-居茶(KERTEH)",
  "JPKAK": "JPKAK-加古川(KAKOGAWA)",
  "JPTKI": "JPTKI-东海(TOKAI)",
  "CNQDG": "CNQDG-青岛大港",
  "JPNMA": "JPNMA-新居滨(NIHAMA)",
  "JPKDA": "JPKDA-神田(KANDA)",
  "BRPAR": "BRPAR-巴拉那瓜(PARANAGUA)",
  "QAMES": "QAMES-麦赛义德(MESAIEED)",
  "KRULS": "KRULS-蔚山(ULSAN)",
  "KRONS": "KRONS-昂山(ONSAN)",
  "IDFUT": "IDFUT-富通(FUTONG)",
  "IDTRH": "IDTRH-打拉根(TARAKAN)",
  "PYPIL": "PYPIL-皮拉尔(PILAR)",
  "NLFLU": "NLFLU-符利辛根",
  "GALOA": "GALOA-GALOA",
  "JPMRG": "JPMRG-MARUGAME丸龟",
  "IDSPH": "IDSPH-塞尼帕",
  "JPUCR": "JPUCR-内浦",
  "JPTSJ": "JPTSJ-对马岛",
  "JPFKJ": "JPFKJ-福井",
  "INDIG": "INDIG-蒂基",
  "KRKHN": "KRKHN-GOHYEON/GEOJE",
  "IDKNW": "IDKNW-科纳韦",
  "JPKMT": "JPKMT-君津",
  "ANCUR": "ANCUR-库拉索",
  "USAXH": "USAXH-亚瑟",
  "USGRY": "USGRY-格拉梅西(gramercy)",
  "ITPMA": "ITPMA-马尔盖腊港(PORTO MARGHERA)",
  "VNNGH": "VNNGH-NGHI SON",
  "GNKAM": "GNKAM-卡姆萨尔(KAMSAR)",
  "OMFAH": "OMFAH-法哈尔(FAHAL)",
  "GNKMR": "GNKMR-卡姆萨尔(KAMSAR)",
  "MYTLS": "MYTLS-丹戎浪塞(TANJUNGLANGSAT)",
  "IDPAW": "IDPAW-巴拉望(PERAWANG)",
  "ZAZ": "ZAZ-萨拉哥萨(zaragoza)",
  "IDMRK": "IDMRK-默拉克(孔雀岛)(MERAK)",
  "CNDJO": "CNDJO-董家口(DONGJIAKOU)",
  "MXTPB": "MXTPB-托波洛万波(TOPOLOBAMPO)",
  "ATAHN": "ATAHN-安铁森霍芬(ANTIESENHOFEN)",
  "JPIMA": "JPIMA-今治(IMABARI)",
  "IDSAM": "IDSAM-三马林达(SAMARINDA)",
  "GQCBA": "GQCBA-吉贝(CEIBA)",
  "TWMAI": "TWMAI-麦寮(MAILIAO)",
  "IDGRE": "IDGRE-格雷西(锦石)(GRESIK)",
  "PEPLO": "PEPLO-洛维托斯(PUNTA LOBITOS)",
  "PHBTN": "PHBTN-巴丹(BATAAN)",
  "INSIK": "INSIK-锡卡(SIKKA)",
  "KRTSN": "KRTSN-瑞山(DAESAN)",
  "MYLAD": "MYLAD-拉哈达图(LAHAD DATU)",
  "JPHTA": "JPHTA-广田(HIROHATA)",
  "JPIHO": "JPIHO-东播磨(HIGASHIHARIMA)",
  "CNYIZ": "CNYIZ-仪征(YIZHENG)",
  "USNWK": "USNWK-纽瓦克(NEWARK)",
  "JPSEN": "JPSEN-仙台(SENDAI)",
  "JOMOJ": "JOMOJ-门司(MOJI)",
  "MYSBT": "MYSBT-沙巴特(SABAHAT)",
  "CLPAG": "CLPAG-安加莫斯(PUERTO ANGAMOS)",
  "NCBDB": "NCBDB-BAIE DE PRONY",
  "NCBAB": "NCBAB-巴布勒特(BABOUILLAT)",
  "QARLF": "QARLF-拉斯拉凡(RAS LAFFAN)",
  "KRWND": "KRWND-莞岛(Wando-gun)",
  "PHSUR": "PHSUR-苏里高(SURIGAO)",
  "SEWAL": "SEWAL-瓦尔港(WALLHAMN)",
  "IRASA": "IRASA-阿萨卢耶(ASALUYEH)",
  "VNVIC": "VNVIC-胡志明",
  "CNCYH": "CNCYH-潮阳海门(Chaoyanghaimen)",
  "CND": "CND-Kogalniceanu",
  "CNDDD": "CNDDD-大磴岛(Dadengdao)",
  "CNHIK": "CNHIK-海口港(Haikou)",
  "CNHMN": "CNHMN-虎门(Humen)",
  "CNHST": "CNHST-黑山头(Heishantou)",
  "CNHUI": "CNHUI-惠州(Huizhou)",
  "CNJAX": "CNJAX-嘉兴(Jiaxing)",
  "CNJLP": "CNJLP-九龙坡港(Jiulongpogang)",
  "CNJMY": "CNJMY-积米崖(Jimiya)",
  "CNJSG": "CNJSG-礁山港(Jiaoshangang)",
  "CNJUZ": "CNJUZ-旧镇(Jiuzhen)",
  "CNLGW": "CNLGW-龙吴(Longwu)",
  "CNLKU": "CNLKU-龙口",
  "CNLSH": "CNLSH-旅顺新港(Lushunxingang)",
  "CNLUB": "CNLUB-萝北(Luobei)",
  "CNLUS": "CNLUS-吕泗(Lusi)",
  "CNLZO": "CNLZO-莱州(Laizhou)",
  "CNMAY": "CNMAY-麻涌(Mayong)",
  "CNMOH": "CNMOH-漠河(Mohe)",
  "CNNAN": "CNNAN-南澳(Nanao)",
  "CNNJG": "CNNJG-南京港(Nanjinggang)",
  "CNNSY": "CNNSY-捻山亚婆角(Nianshanyapojiao)",
  "CNPGZ": "CNPGZ-平洲(Pingzhou)",
  "CNQLN": "CNQLN-清澜(Qinglan)",
  "CNQSA": "CNQSA-企沙(Qisha)",
  "CNQZH": "CNQZH-钦州(Qinzhou)",
  "CNRGC": "CNRGC-榕城(Rongcheng)",
  "CNSBM": "CNSBM-三百门(Sanbaimen)",
  "CNSHG": "CNSHG-上海港(Shanghaigang)",
  "CNSHX": "CNSHX-三水西南(Sanshuixinan)",
  "CNSIQ": "CNSIQ-赛歧(Saiqi)",
  "CNSKS": "CNSKS-四块石(Sikuaishi)",
  "CNSNW": "CNSNW-神湾(Shenwan)",
  "CNSTG": "CNSTG-汕头港(Shantougang)",
  "CNSWI": "CNSWI-室韦(Shiwei)",
  "CNTAP": "CNTAP-**太平(Taiping)",
  "FRSML": "FRSML-圣马洛(St Malo)",
  "FKPSY": "FKPSY-斯坦利港(Port Stanley)",
  "FRMRS": "FRMRS-马赛(Marseille)",
  "FRNTE": "FRNTE-南特(Nantes)",
  "GALBV": "GALBV-利伯维尔/利博维尔(Libreville)",
  "GBBEL": "GBBEL-贝尔法斯特(Belfast)",
  "GBBOS": "GBBOS-波士顿(Boston)",
  "GBDUN": "GBDUN-邓迪/丹迪(Dundee)",
  "GBG": "GBG-Galesburg Municiple Airport",
  "GBHTP": "GBHTP-哈特尔浦(Hartlepool)",
  "GBLDY": "GBLDY-伦敦德里(Londonderry)",
  "GBMTH": "GBMTH-梅西尔/麦迪尔(Methil)",
  "GBNPT": "GBNPT-纽波特(Newport)",
  "GBSWA": "GBSWA-斯旺西(Swansea)",
  "GBTIL": "GBTIL-蒂尔伯里/蒂尔博里(Tilbury)",
  "GDSTG": "GDSTG-圣乔治(Saint George's)",
  "ESAGP": "ESAGP-马拉加(Malaga)",
  "GEPTI": "GEPTI-波季(Poti)",
  "DKHLS": "DKHLS-赫尔辛格(Helsingor)",
  "ESALG": "ESALG-阿尔赫西拉斯(Algeciras)",
  "DZALG": "DZALG-阿尔及尔(Alger (Algiers))",
  "EAR": "EAR-Kearney Municipal Airport",
  "CUCAI": "CUCAI-凯巴连(Caibarien)",
  "ECBHA": "ECBHA-卡拉克斯湾/卡腊克斯港(Bahia de Caraquez)",
  "ECMEC": "ECMEC-曼塔(Manta)",
  "ECSNC": "ECSNC-萨利纳斯(Salinas)",
  "EEN": "EEN-Dillant Hopkins",
  "EFD": "EFD-Ellington Field",
  "EGADA": "EGADA-阿代比耶/阿巴比亚/阿达比亚(Adabiya)",
  "EGDAM": "EGDAM-杜姆亚特/达米埃塔(Damietta)",
  "EGPSD": "EGPSD-塞得港(Port Said)",
  "EGRAG": "EGRAG-拉斯加里卜/腊斯加里卜(Ras Gharib)",
  "EHVIC": "EHVIC-达赫拉(Ad Dakhla)",
  "QAUMS": "QAUMS-乌姆赛义德(QAPCO, UMM SALAL)",
  "IDKTG": "IDKTG-库拉坦姜(KUALA TANJUNG)",
  "USPHU": "USPHU-怀尼米港(PORT HUENEME)",
  "IDGOR": "IDGOR-哥伦打洛(GORONTALO)",
  "USCRP": "USCRP-科珀斯克里斯蒂(CORPUS CHRISTI)",
  "NLDOR": "NLDOR-多尔德雷赫特(DORDRECHT)",
  "ESBIO": "ESBIO-毕尔巴鄂(Bilbao)",
  "ESC": "ESC-Delta County Airport",
  "ESGIJ": "ESGIJ-希洪(Gijon)",
  "ESLCG": "ESLCG-拉科鲁尼亚(La Coruna)",
  "ESLPA": "ESLPA-拉斯帕尔马斯(Las Palmas)",
  "ESPAS": "ESPAS-帕萨赫斯(Pasajes)",
  "ESR": "ESR-El Salvador",
  "ESSCT": "ESSCT-圣克鲁斯(Santa Cruz de Tenerife)",
  "ESSVQ": "ESSVQ-塞维利亚(Sevilla)",
  "ESVGO": "ESVGO-维哥(Vigo)",
  "CUCFG": "CUCFG-西恩富戈斯(Cienfuegos)",
  "CUMZO": "CUMZO-曼萨尼略(Manzanillo)",
  "FIHKO": "FIHKO-汉科(Hango (Hanko))",
  "FIKEM": "FIKEM-凯米/盖密(Kemi/Tornio (Kemi/Tornea))",
  "FIKTK": "FIKTK-科特卡(Kotka)",
  "FITKU": "FITKU-图尔库(Turku (Abo))",
  "XEJ": "XEJ-Langford / Via Rail Service",
  "CNYZH": "CNYZH-扬州(Yangzhou)",
  "CNZGT": "CNZGT-中堂(Zhongtang)",
  "CNZNG": "CNZNG-湛江港(Zhanjianggang)",
  "CNZXZ": "CNZXZ-漳州下寨(Zhangzhouxiazhai)",
  "COK": "COK-Naval Air Station",
  "COPCR": "COPCR-卡雷尼奥港(Puerto Carreno)",
  "COTRB": "COTRB-图尔博(Turbo)",
  "AUBNE": "AUBNE-布里斯班(Brisbane)",
  "AUDAM": "AUDAM-丹皮尔(Dampier)",
  "AUGET": "AUGET-杰拉尔顿(Geraldton)",
  "AUGLT": "AUGLT-格拉德斯通(Gladstone)",
  "AUMKY": "AUMKY-麦凯(Mackay)",
  "AUPLO": "AUPLO-林肯港(Port Lincoln)",
  "AUS": "AUS-Robert Mueller Municipal Airport",
  "AUWYA": "AUWYA-怀阿拉(Whyalla)",
  "AVL": "AVL-Asheville Regional Airport",
  "BRFOR": "BRFOR-福塔莱萨/福塔雷萨(Fortaleza)",
  "BRIBB": "BRIBB-因比图巴/因比土巴(Imbituba)",
  "BEZEE": "BEZEE-泽布吕赫/泽布腊赫(Zeebrugge)",
  "BRITJ": "BRITJ-伊塔雅伊(Itajai)",
  "BGNES": "BGNES-纳塞巴尔/尼萨巴/奈萨巴港(Nessebar)",
  "BHMAN": "BHMAN-麦纳麦(Al Manamah/ Manama)",
  "BRBEL": "BRBEL-贝伦(Belem)",
  "BHSIT": "BHSIT-锡特拉(Sitra)",
  "NOFUS": "NOFUS-菲萨(FUSA)",
  "BRIOA": "BRIOA-伊塔波(ITAPOA)",
  "RUNJK": "RUNJK-纳霍德卡(NAKHODKA)",
  "CNJIG": "CNJIG-靖江(JINGJIANG)",
  "ARUSH": "ARUSH-乌斯怀亚(Ushuaia)",
  "BRNTR": "BRNTR-尼泰罗伊(Niteroi)",
  "AUBWT": "AUBWT-伯尼(BURNIE)",
  "AUPKL": "AUPKL-肯布拉港(PORT KEMBLA)",
  "AUPTL": "AUPTL-阿尔马港(PORT ALMA)",
  "EGAIS": "EGAIS-苏科纳(SOKHNA)",
  "SEGOT": "SEGOT-哥德堡(GOTHENBURG)",
  "GBSSH": "GBSSH-南希尔兹(SOUTH SHIELDS)",
  "BRPDU": "BRPDU-乌布角(PONTA DO UBU)",
  "CUBGR": "CUBGR-博卡格兰德(BOCA GRANDE)",
  "JPMYK": "JPMYK-宫古(MIYAKO)",
  "IDPER": "IDPER-帕拉旺(PERAWANG)",
  "NCTOE": "NCTOE-特奥迪伊(TEOUDIE)",
  "BRIGI": "BRIGI-伊塔瓜亚(ITAGUAI)",
  "AUPGI": "AUPGI-吉利港(PORT GILES)",
  "CASYD": "CASYD-悉尼(Sydney)",
  "BRPOA": "BRPOA-阿雷格里港/阿里格(Porto Alegre)",
  "BRRIG": "BRRIG-里奥格兰德(Rio Grande)",
  "CATOR": "CATOR-多伦多(Toronto)",
  "BRSFS": "BRSFS-南圣弗兰西斯科/富兰克斯考(Sao Francisco do Sul)",
  "BRSSZ": "BRSSZ-桑托斯/圣多斯(Santos)",
  "BRT": "BRT-Bathurst Island",
  "BSFPO": "BSFPO-弗里波特(Freeport)",
  "CAVAN": "CAVAN-温哥华(Vancouver)",
  "CLCQQ": "CLCQQ-科金博(Coquimbo)",
  "CLMJS": "CLMJS-梅希约内斯(Mejillones)",
  "CLO": "CLO-Alfonso Bonilla Aragon",
  "CLQMC": "CLQMC-奎姆什(Quemchi)",
  "CLTAL": "CLTAL-塔尔卡瓦诺/塔尔卡瓦纳(Talcahuano)",
  "CLWCA": "CLWCA-卡斯特罗(Castro)",
  "CMDLA": "CMDLA-杜阿拉(Douala)",
  "CIABJ": "CIABJ-阿比让(Abidjan)",
  "CLCLD": "CLCLD-卡尔德拉(Caldera)",
  "CMTKC": "CMTKC-提科/蒂科(Tiko)",
  "CNAJG": "CNAJG-鏊江港(Aojianggang)",
  "CNBZG": "CNBZG-渤中(Bozhong)",
  "AUKRB": "AUKRB-卡伦巴(KARUMBA)",
  "AEARS": "AEARS-RUWAIS",
  "THKSC": "THKSC-考斯昌(HSICHANG)",
  "PHJIM": "PHJIM-吉门尼兹(JIMENEZ)",
  "PTMDA": "PTMDA-马德拉(MADEIRA)",
  "IDSMQ": "IDSMQ-桑皮特(SAMPIT)",
  "PHGIN": "PHGIN-金古格(GINGOOG)",
  "JPNAO": "JPNAO-直江津(NAOETSU)",
  "OMSOH": "OMSOH-索哈(SOHAR)",
  "DKSVE": "DKSVE-斯文堡(SVENDBORG)",
  "MYTPP": "MYTPP-丹戎帕拉帕斯(TANJUNG PELEPAS)",
  "USLON": "USLON-朗维尤(LONGVIEW)",
  "KRINC": "KRINC-仁川(Incheon)",
  "CVRAI": "CVRAI-普拉亚(Praia)",
  "DKAAR": "DKAAR-奥尔胡斯(Arhus/Aarhus)",
  "AIROA": "AIROA-路德湾(The Road)",
  "ALSHG": "ALSHG-圣吉尼(Shengjin)",
  "AOLAD": "AOLAD-罗安达(Luanda)",
  "AOPLE": "AOPLE-亚历山大港(Porto Alexandre (Tombua))",
  "APN": "APN-Alpena Regional Airport",
  "ARCMP": "ARCMP-坎帕纳(Campana)",
  "DEBRV": "DEBRV-不来梅港(Bremerhaven)",
  "DECGN": "DECGN-科隆(Koln/ Cologne)",
  "DEKEL": "DEKEL-基尔(Kiel)",
  "BRNAT": "BRNAT-纳塔尔(Natal)",
  "BRPET": "BRPET-佩洛塔斯(Pelotas)",
  "BRPNG": "BRPNG-巴拉那瓜(Paranagua)",
  "ROSUL": "ROSUL-苏利纳(Sulina)",
  "BRREC": "BRREC-累西腓(Recife)",
  "BRRIO": "BRRIO-里约热内卢(Rio de Janeiro)",
  "BRSLZ": "BRSLZ-圣路易斯/路易斯(Sao Luis)",
  "BRSSA": "BRSSA-萨尔瓦多(Salvador)",
  "ROBRA": "ROBRA-布勒伊拉(Braila)",
  "ROCND": "ROCND-康斯坦萨(Constantza/ Constanta)",
  "ROMAG": "ROMAG-曼加利亚/曼格利亚(Mangalia)",
  "DEWVN": "DEWVN-威廉港(Wilhelmshaven)",
  "CDMAT": "CDMAT-马塔迪(Matadi)",
  "RUARH": "RUARH-阿尔汉格尔/阿尔汉格尔斯克(Archangel/ Arkhangelsk)",
  "RUDYR": "RUDYR-阿纳德尔(Anadyr)",
  "RUKGD": "RUKGD-加里宁格勒(Kaliningrad)",
  "RUKHO": "RUKHO-霍尔姆斯克(Kholmsk)",
  "RUKOR": "RUKOR-科尔萨科夫(Korsakov)",
  "RULED": "RULED-圣彼得堡/列宁格勒(ST. Petersburg /Leningrad)",
  "RUMAG": "RUMAG-马加丹(Magadan/ Magadansky, Port)",
  "RUMMK": "RUMMK-摩尔曼斯克(Murmansk)",
  "RUNEV": "RUNEV-涅韦尔斯克(Nevelsk)",
  "RUNVS": "RUNVS-新罗西斯克/诺沃罗西斯克(Novorossisk/ Novorossiysk)",
  "RUOHO": "RUOHO-鄂霍次克(Okhotsk)",
  "RUPKC": "RUPKC-彼得罗巴浦洛夫斯克(Petropavlovsk)",
  "RUROV": "RUROV-罗斯托夫(Rostov)",
  "RUSOC": "RUSOC-索契(Sochi)",
  "RUTUA": "RUTUA-图阿普谢(Tuapse)",
  "RUVYP": "RUVYP-东方港(Vostochnyy/ Vostochniy, Port)",
  "SADMM": "SADMM-达曼(Damman/ Ad Dammam)",
  "SAH": "SAH-International",
  "SAJUB": "SAJUB-朱拜勒(Jubail)",
  "SBHIR": "SBHIR-霍尼亚拉(Honiara)",
  "SBSHH": "SBSHH-肖特兰岛(Shortland Harbour)",
  "SEHAD": "SEHAD-哈尔姆斯塔德(Halmstad)",
  "SELLA": "SELLA-吕勒奥/陆勒奥(Lulea)",
  "SEMMA": "SEMMA-马尔默(Malmo)",
  "SEPIT": "SEPIT-皮特奥/皮特欧(Pitea)",
  "SESTO": "SESTO-斯德哥尔摩(Stockholm)",
  "SEUME": "SEUME-于默奥/乌米(Umea)",
  "INVTZ": "INVTZ-维沙卡帕特南(Visakhapatnam)",
  "IRBKM": "IRBKM-霍梅尼港(Bandar Khomeini)",
  "IRKHK": "IRKHK-哈尔克岛(Kharg Island/ Khark Island)",
  "ISAKU": "ISAKU-阿克雷里/阿库雷里(Akureyri)",
  "ISREY": "ISREY-雷克雅未克(Reykjavik)",
  "ITAUG": "ITAUG-奥古斯塔(Augusta)",
  "ITCTA": "ITCTA-卡塔尼亚(Catania)",
  "ITFCO": "ITFCO-菲乌米奇诺(Fiumicino)",
  "ITMSN": "ITMSN-墨西拿(Messina)",
  "ITPFX": "ITPFX-萨罗奇/福克西港(Sarroch (Porto Foxi))",
  "ITSVN": "ITSVN-萨沃纳(Savona/ Funivie)",
  "JESTH": "JESTH-圣赫利尔/圣海利尔(St Helier)",
  "JMPOT": "JMPOT-安东尼奥港(Port Antonio)",
  "JPCHB": "JPCHB-千叶(Chiba)",
  "JPHHE": "JPHHE-八户(Hachinohe)",
  "JPHMD": "JPHMD-滨田(Hamada)",
  "JPIWK": "JPIWK-岩国(Iwakuni)",
  "JPKOJ": "JPKOJ-鹿儿岛(Kagoshima)",
  "JPNGO": "JPNGO-名古屋(Nagoya)",
  "JPOSA": "JPOSA-大阪(Osaka)",
  "JPSMZ": "JPSMZ-清水(Shimizu)",
  "JPTMK": "JPTMK-苫小牧(Tomakomai)",
  "JPYKK": "JPYKK-四日市(Yokkaichi)",
  "KELAU": "KELAU-拉穆(Lamu)",
  "KEMYD": "KEMYD-马林迪(Malindi)",
  "KHKOS": "KHKOS-磅逊(Kompong Som/ Kampong Saom)",
  "KHN": "KHN-南昌昌北机场(Nanchangchangbeijichang)",
  "PETRU": "PETRU-特鲁希略(Trujillo)",
  "PGPOM": "PGPOM-莫尔兹比港(Port Moresby)",
  "PHMNL": "PHMNL-马尼拉(Manila)",
  "PHSFE": "PHSFE-圣弗尔南多(San Fernando)",
  "MDJ": "MDJ-牡丹江海浪机场(Mudanjianghailangjichang)",
  "MGMOQ": "MGMOQ-穆龙达瓦(Morondava)",
  "MHMAJ": "MHMAJ-马朱罗环礁/马朱罗(Majuro)",
  "PLGDY": "PLGDY-格丁尼亚(Gdynia)",
  "PLSWI": "PLSWI-希维诺乌伊希切/斯维诺斯切(Swinoujscie)",
  "JPKMA": "JPKMA-鹿岛(KASHIMA)",
  "VNDQT": "VNDQT-榕橘(DUNG QUAT PORT)",
  "VUVLI": "VUVLI-维拉港/威拉(Port Vila/Vila)",
  "WFMAU": "WFMAU-马塔乌图(Mata'utu)",
  "WNZ": "WNZ-温州永强机场(Wenzhouyongqiangjichang)",
  "HHN": "HHN-法兰克福哈恩机场(HAHNAIRPORT)",
  "DOSPM": "DOSPM-圣佩得罗德马科里斯(San Pedro de Macoris)",
  "DZORN": "DZORN-奥兰/瓦赫兰(Oran/Wahran)",
  "ECESM": "ECESM-埃斯梅拉达斯/埃斯梅腊达斯(Esmeraldas)",
  "EETLL": "EETLL-塔林(Tallinn)",
  "EGALY": "EGALY-亚历山大/亚历山德里亚(El Iskandariya (= Alexandria))",
  "EGSUZ": "EGSUZ-苏伊士(El Suweis (= Suez))",
  "ERMSW": "ERMSW-马萨瓦(Massawa (Mitsiwa))",
  "ESALC": "ESALC-阿利坎特(Alicante)",
  "ESBCN": "ESBCN-巴塞罗那(Barcelona)",
  "ESCAR": "ESCAR-卡塔赫纳(Cartagena)",
  "ESFUE": "ESFUE-罗萨里奥港(Puerto del Rosario-Fuerteventura)",
  "ESPMI": "ESPMI-帕尔马(Palma de Mallorca)",
  "ESSDR": "ESSDR-桑坦德(Santander)",
  "ESVLC": "ESVLC-巴伦西亚(Valencia)",
  "SELAA": "SELAA-兰斯克鲁纳/朗茨克鲁纳(Landskrona)",
  "SEOER": "SEOER-恩舍尔兹维克/奥斯克德斯维克(Ornskoldsvik)",
  "SHA": "SHA-上海虹桥国际机场(Shanghaihongqiaoguojijichang)",
  "SVAQJ": "SVAQJ-阿卡胡特拉(Acajutla)",
  "TGKPE": "TGKPE-佩梅/克佩美(Kpeme)",
  "IDTAI": "IDTAI-打拉根(TARAKAN ISLAND)",
  "PYTER": "PYTER-特尔港(TERPORT)",
  "XMN": "XMN-厦门高崎国际机场(Xiamengaoqiguojijichang)",
  "SYTTS": "SYTTS-他图斯/塔尔图斯(Tartous/ Tartus)",
  "SZX": "SZX-深圳宝安国际机场(Shenzhenbaoanguojijichang)",
  "THNAW": "THNAW-那拉提瓦(Narathiwat)",
  "THSGZ": "THSGZ-宋卡(Songkh1a)",
  "TNA": "TNA-济南遥墙机场(Jinanyaoqiangjichang)",
  "TNSUS": "TNSUS-苏萨/苏塞(Sousse/Soussa)",
  "TOTBU": "TOTBU-努库阿洛法(Nuku'alofa)",
  "USANC": "USANC-安科雷奇(Anchorage)",
  "GHTKD": "GHTKD-塔科拉迪(Takoradi)",
  "GLGOH": "GLGOH-戈特霍布(Nuuk (Godthaab))",
  "GLUAK": "GLUAK-纳萨尔苏瓦克/纳萨苏克(Narsarsuaq)",
  "UAILK": "UAILK-伊利切维斯克(Ilichevsk/ Illichivs'k)",
  "UAUDY": "UAUDY-乌斯列戈尔斯克(Ust-Dunaysk/ Ust Dunaysk)",
  "USHOU": "USHOU-休斯敦(Houston)",
  "USJAX": "USJAX-杰克逊维尔(Jacksonville)",
  "USMEM": "USMEM-孟菲斯(Memphis)",
  "USNBD": "USNBD-新贝德福德(New Bedford)",
  "USPWM": "USPWM-波特兰(Portland)",
  "USSAN": "USSAN-圣迭戈/圣地亚哥(San Diego)",
  "USTXT": "USTXT-得克萨斯城(Texas City)",
  "UYPDP": "UYPDP-埃斯特角(Punta del Este)",
  "VEAMY": "VEAMY-阿穆艾湾/阿木艾(Amuay/Amuay Bay)",
  "VEPCN": "VEPCN-篷塔卡尔东/卡东角(Punta Cardon)",
  "VNCRB": "VNCRB-金兰(Camranh)",
  "VNHUI": "VNHUI-顺化(Hue)",
  "VNSGN": "VNSGN-胡志明市(Ho Chi Minh City)",
  "CNWHZ": "CNWHZ-威海张家埠(Weihaizhangjiabu)",
  "CNZQG": "CNZQG-肇庆港(Zhaoqinggang)",
  "CNDXG": "CNDXG-大连新港(Dalianxingang)",
  "CNGYN": "CNGYN-高要南岸(Gaoyaonanan)",
  "CNLNS": "CNLNS-澜石(Lanshi)",
  "CNQNH": "CNQNH-琼海潭门(Qionghaitanmen)",
  "CNSTJ": "CNSTJ-沙头角(Shatoujiao)",
  "CLCBC": "CLCBC-卡布尔科(CALBUCO)",
  "DKTHD": "DKTHD-托尔莎温(TORSHAVN)",
  "PHSBC": "PHSBC-苏比克(SUBIC)",
  "TREYP": "TREYP-艾维亚普港(EVYAP PORT)",
  "IDAGA": "IDAGA-阿格斯(AGATS)",
  "IDBXT": "IDBXT-邦坦(BONTANG，KL)",
  "MYKLA": "MYKLA-巴生(KLANG)",
  "MYKTR": "MYKTR-瓜拉丁加奴(KUALA TERENGGANU)",
  "CNDIN": "CNDIN-定海(Dinghai)",
  "NGPHC": "NGPHC-哈科特港(Port Harcourt)",
  "NIPUZ": "NIPUZ-卡贝萨斯港(Puerto Cabezas)",
  "NLDZL": "NLDZL-德尔夫宰尔(Delfzijl/Delfzyl)",
  "NLVLI": "NLVLI-符利辛根/符拉辛(Vlissingen/Flushing)",
  "NOFRK": "NOFRK-腓特烈斯塔(Fredrikstad)",
  "NOHRD": "NOHRD-哈尔斯塔(Harstad)",
  "NOKKN": "NOKKN-希尔克内斯/基尔克内斯(Kirkenes)",
  "NOSVG": "NOSVG-斯塔西勒/斯塔万格(Stavanger)",
  "NUIUE": "NUIUE-纽埃岛(Niue Island)",
  "NZBLU": "NZBLU-布拉夫(Bluff)",
  "NZGIS": "NZGIS-吉斯珀恩/基斯博恩(Gisborne)",
  "NZOPX": "NZOPX-奥普阿/奥普瓦(Opua)",
  "AUHAY": "AUHAY-海角(HAY POINT)",
  "USCVT": "USCVT-康文特(CONVENT)",
  "CNJTG": "CNJTG-京唐港(Jingtanggang)",
  "CNJZK": "CNJZK-荆州盐卡(Jingzhouyanka)",
  "CNLIH": "CNLIH-莲花山(Lianhuashan)",
  "CNLSX": "CNLSX-陵水新村(Lingshuixincun)",
  "CNLZL": "CNLZL-雷州流沙(Leizhouliusha)",
  "CNMOT": "CNMOT-庙头(Miaotou)",
  "CNNHS": "CNNHS-南海三山港(Nanhaisanshangang)",
  "CNNSA": "CNNSA-南沙(Nansha)",
  "CNPAJ": "CNPAJ-盘锦(Panjin)",
  "CNPTJ": "CNPTJ-平潭金井(Pingtanjinjing)",
  "CNPXM": "CNPXM-平沙新码头(Pingshaxinmatou)",
  "CNQZJ": "CNQZJ-泉州(Quanzhou)",
  "CNSBU": "CNSBU-三埠(Sanbu)",
  "CNSHD": "CNSHD-石岛(Shidao)",
  "CNSHP": "CNSHP-秦皇岛(Qinhuangdao)",
  "CNSJI": "CNSJI-泗礁(Sijiao)",
  "CNSNH": "CNSNH-深沪(Shenhu)",
  "CNSON": "CNSON-松下(Songxia)",
  "CNSTI": "CNSTI-沙田(Shatian)",
  "CNSXB": "CNSXB-遂溪北潭(Suixibeitan)",
  "CNTBS": "CNTBS-天津保税区(Tianjinbaoshuiqu)",
  "FMPNI": "FMPNI-波纳佩(Pohnpei (ex Ponape))",
  "FOTHO": "FOTHO-托尔斯港(Thorshavn)",
  "FRAJA": "FRAJA-阿雅克修(Ajaccio)",
  "FRBES": "FRBES-布雷斯特(Brest)",
  "FRBOD": "FRBOD-波尔多(Bordeaux)",
  "FRBOL": "FRBOL-布洛涅/布伦(Boulogne-sur-Mer)",
  "FRDKK": "FRDKK-敦刻尔克(Dunkerque)",
  "FRFOS": "FRFOS-福斯(Fos-sur-Mer)",
  "GGSPT": "GGSPT-圣彼德港/圣彼得港(St Peter Port)",
  "GLJEG": "GLJEG-埃格瑟斯明讷/埃格德斯米纳(Aasiaat (Egedesminde))",
  "MMKYP": "MMKYP-皎漂(Kyaukpyu)",
  "MMMNU": "MMMNU-毛淡棉(Moulmein/ Mawlamyine)",
  "NZPOE": "NZPOE-查马斯港/查尔莫斯港(Port Chalmers)",
  "NZWAV": "NZWAV-韦弗利港/韦沃雷港(Waverley Harbour)",
  "RUSKT": "RUSKT-莎克特斯克(SHAKHTERSK)",
  "HET": "HET-呼和浩特白塔国际机场(Huhehaote Baita International Airport)",
  "HNPCA": "HNPCA-卡斯蒂利亚港/卡斯提利亚港(Puerto Castilla)",
  "HRPLE": "HRPLE-卡德尔耶沃/普洛切(Kardeljevo/ Ploce)",
  "IDBJU": "IDBJU-巴纽旺宣(Banjuwangi)",
  "IDDJJ": "IDDJJ-查亚普拉(Jayapura)",
  "IDPEX": "IDPEX-北加浪岸(Pekalongan)",
  "IDPNK": "IDPNK-坤甸(Pontianak)",
  "IDSRG": "IDSRG-三宝垄(Semarang)",
  "IDTBR": "IDTBR-直落巴由(Telukbayur)",
  "IEDLG": "IEDLG-敦劳费尔/邓莱里(Dun Laoghaire)",
  "IEORK": "IEORK-科克(Cork)",
  "ILETH": "ILETH-埃拉特(Eilat(Eilath))",
  "IQUQR": "IQUQR-乌姆盖斯尔/乌姆卡斯尔(Umm Qasr)",
  "IRKHO": "IRKHO-胡宁沙赫尔(原名霍拉姆沙赫尔)(Khorramshahr)",
  "BRFNA": "BRFNA-FAZENDA NOVA",
  "PAMIT": "PAMIT-Manzanillo",
  "TKAFU": "TKAFU-Atafu",
  "GBABD": "GBABD-阿伯丁(Aberdeen)",
  "GBBID": "GBBID-比迪福德/比德福德(Bideford)",
  "GBBRS": "GBBRS-布里斯托尔(Bristol)",
  "GBCYP": "GBCYP-克莱德港(Clydeport)",
  "GBDVR": "GBDVR-多佛/多佛尔(Dover)",
  "GBFXT": "GBFXT-弗利克斯托(Felixstowe)",
  "GBGLW": "GBGLW-格拉斯哥(Glasgow)",
  "GBGRG": "GBGRG-格兰奇茅斯(Grangemouth)",
  "GBHRW": "GBHRW-哈里奇/哈里季(Harwich)",
  "GBHUL": "GBHUL-赫尔(Hull)",
  "GBIPS": "GBIPS-伊普斯威奇(Ipswich)",
  "GBLEI": "GBLEI-利斯(Leith)",
  "GBLIV": "GBLIV-利物浦(Liverpool)",
  "GBMLF": "GBMLF-米尔福德港(Milford Haven)",
  "GBMNC": "GBMNC-曼彻斯特(Manchester)",
  "GBNCL": "GBNCL-纽卡斯尔(Newcastle upon Tyne)",
  "GBPLY": "GBPLY-普利茅斯(Plymouth)",
  "GBSHO": "GBSHO-肖勒姆(Shoreham)",
  "GBSOU": "GBSOU-南安普顿(Southampton)",
  "GBSUN": "GBSUN-森德兰/桑德兰(Sunderland)",
  "GBTEE": "GBTEE-提斯港(Teesport)",
  "TTPOS": "TTPOS-西班牙港(Port-of-Spain)",
  "RUNAK": "RUNAK-纳霍德卡(NAKHODKA)",
  "DKRIB": "DKRIB-里伯(RIBE)",
  "INGGV": "INGGV-冈加哈帕纳姆(GANGAVARAM)",
  "PHCYP": "PHCYP-卡尔贝扬(CALBAYOG)",
  "RUPSE": "RUPSE-波塞特(POSYET)",
  "RICMD": "RICMD-列治文(RICHMOND)",
  "CYFMG": "CYFMG-阿莫霍斯托斯(原称法马斯塔)(Famagusta)",
  "DEEME": "DEEME-埃姆登(Emden)",
  "DERSK": "DERSK-罗斯托克(Rostock)",
  "DJJIB": "DJJIB-吉布提(Djibouti)",
  "AGSJO": "AGSJO-圣约翰斯(Saint John' s)",
  "AOCAB": "AOCAB-卡宾达(Cabinda)",
  "AOMSZ": "AOMSZ-内米贝/纳米比(Namibe)",
  "AONDD": "AONDD-新里东杜(苏布/SUMBE)(Sumbe（Novo Redondo）)",
  "RUPRN": "RUPRN-波罗奈斯克(Poronaisk)",
  "RUTAG": "RUTAG-塔甘罗格(Taganrog)",
  "RUUKK": "RUUKK-乌斯季堪察茨克(Ust-Kamchatsk)",
  "RUZAR": "RUZAR-扎鲁比诺(Zarubino)",
  "SAGIZ": "SAGIZ-季赞(Glzan/ Jizan)",
  "SAYNB": "SAYNB-延布(Yenbo/ Yanbu al-Bahr)",
  "SEGVX": "SEGVX-格夫勒/耶夫勒(Gavle)",
  "SEKAA": "SEKAA-卡尔斯克鲁纳(Karlskrona)",
  "SEKAN": "SEKAN-卡尔斯港/卡尔斯哈门(Karlshamn)",
  "SEOXE": "SEOXE-乌克瑟勒松德/奥克斯洛松德(Oxelosund)",
  "SGSIN": "SGSIN-新加坡(Singapore)",
  "MUPLU": "MUPLU-路易港(Port Louis)",
  "PHBTG": "PHBTG-八打雁(Batangas)",
  "PHCEB": "PHCEB-宿务(Cebu)",
  "PHCGY": "PHCGY-卡加延德奥罗(Cagayan de Oro)",
  "PKBQM": "PKBQM-卡希姆港/卡希姆/穆哈马德宾卡西姆港(Muhammad Bin Qasim/Karachi)",
  "PMFSP": "PMFSP-圣皮埃尔(St Pierre)",
  "OMMCT": "OMMCT-马斯喀特(Muscat)",
  "OMMUT": "OMMUT-马特拉/马特腊(Muttrah/ Muthra)",
  "OMRAY": "OMRAY-赖苏特港(Raysut/Mina Raysut)",
  "ORH": "ORH-Worcester /James D O''brien Field(Worcester /James D O'brien Field)",
  "PAPAM": "PAPAM-阿尔米兰特(Almirante)",
  "PEEEN": "PEEEN-埃腾(Eten)",
  "PEMLQ": "PEMLQ-莫延多/莫廉多(Mollendo)",
  "IDCXP": "IDCXP-芝拉扎(Cilacap)",
  "IDPDG": "IDPDG-巴东(Padang)",
  "IDPKS": "IDPKS-庞卡兰苏苏(Pangkalan Susu)",
  "IDSBG": "IDSBG-沙璜(Sabang)",
  "IDTJQ": "IDTJQ-丹戎潘丹(Tanjung Pandan)",
  "CAVIC": "CAVIC-维多利亚(Victoria)",
  "CDBNW": "CDBNW-巴纳纳(Banana)",
  "CGDJE": "CGDJE-哲诺油码头/杰诺港(Djeno Terminal)",
  "CIZSS": "CIZSS-萨桑德拉(Sassandra)",
  "CKARU": "CKARU-阿鲁通加/艾图塔基(Arutunga)",
  "CLARI": "CLARI-阿里卡(Arica)",
  "CLCNR": "CLCNR-查尼亚拉尔/查尼亚腊尔(Chanaral)",
  "CLPMC": "CLPMC-蒙特港(Puerto Montt)",
  "CLPUQ": "CLPUQ-阿雷纳斯角/彭塔阿雷纳斯(Punta Arenas)",
  "CLVAP": "CLVAP-瓦尔帕莱索(Valparaiso)",
  "CNBIJ": "CNBIJ-北窖(Beijiao)",
  "CNBSP": "CNBSP-八所(Basuo)",
  "CNCLJ": "CNCLJ-城陵矶(Chenglingji)",
  "CNCWN": "CNCWN-赤湾(Chiwan)",
  "CNDBX": "CNDBX-电白县博贺(Dianbaixianbohe)",
  "CNDDG": "CNDDG-丹东港(Dandonggang)",
  "CNDFG": "CNDFG-大丰(Dafeng)",
  "CNDGU": "CNDGU-冬古(Donggu)",
  "CNDJG": "CNDJG-东疆港区(Dongjianggangqu)",
  "CNDMX": "CNDMX-斗门新环(Doumenxinhuan)",
  "CNDSG": "CNDSG-岱山高亭(Daishangaoting)",
  "CNDTZ": "CNDTZ-大台子(Dataizi)",
  "CNDZM": "CNDZM-丹纸码头(Danzhimatou)",
  "CNFAN": "CNFAN-防城(Fangcheng)",
  "CNFKJ": "CNFKJ-封开江口港(Fengkaijiangkouan)",
  "CNFZL": "CNFZL-福州罗沅淡头(Fuzhouluoyuandantou)",
  "CNGHI": "CNGHI-广海(Guanghai)",
  "CNCHI": "CNCHI-池洲(Chizhou)",
  "TRGIR": "TRGIR-古雷松/吉雷孙(Giresun)",
  "CNTXG": "CNTXG-天津新港(Tianjingang)",
  "CNWEF": "CNWEF-潍坊(Weifang)",
  "CNWGQ": "CNWGQ-外高桥保税区(Waigaoqiao)",
  "CNWHR": "CNWHR-威海乳山(Weihairushan)",
  "CNWUG": "CNWUG-吴淞(Wusong)",
  "CNWUX": "CNWUX-无锡(Wuxi)",
  "CNWZO": "CNWZO-温州(Wenzhou)",
  "CNXAS": "CNXAS-霞山(Xiashan)",
  "CNXGZ": "CNXGZ-香州(Xiangzhou)",
  "CNXIT": "CNXIT-新塘(Xintang)",
  "CNXML": "CNXML-厦门刘五店(Xiamenliuwudian)",
  "CNXWH": "CNXWH-徐闻海安(Xuwenhaian)",
  "CNYGK": "CNYGK-羊口(Yangkou)",
  "CNYPG": "CNYPG-洋浦(Yangpu)",
  "CNZEL": "CNZEL-柘林(Zhelin)",
  "CNZHE": "CNZHE-镇江(Zhenjiang)",
  "CNZOS": "CNZOS-舟山(Zhoushan)",
  "CNZUH": "CNZUH-珠海(Zhuhai)",
  "COBUN": "COBUN-布韦那文图拉(Buenaventura)",
  "COSMR": "COSMR-圣玛尔塔/圣马尔塔(Santa Marta)",
  "CRGLF": "CRGLF-戈尔菲托/格尔菲托(Golfito)",
  "CRPAS": "CRPAS-彭塔雷纳斯(Puntarenas)",
  "CUANT": "CUANT-安蒂亚/安蒂利亚(Antilla)",
  "CUICR": "CUICR-尼卡罗(Nicaro)",
  "CUQMA": "CUQMA-马坦萨斯/马但萨斯(Matanzas)",
  "CYLCA": "CYLCA-拉纳卡(Larnaca)",
  "CYPFO": "CYPFO-佩福斯/帕福斯(Paphos)",
  "DEBRB": "DEBRB-布龙斯比特尔/布朗斯布特尔(Brunsbuttel)",
  "DEWIS": "DEWIS-维斯马(Wismar)",
  "AEDXB": "AEDXB-迪拜(Dubai)",
  "USMSY": "USMSY-新奥尔良(New Orleans)",
  "USOAK": "USOAK-奥克兰(Oakland)",
  "USPSM": "USPSM-朴次茅斯(Portsmouth)",
  "ITCVV": "ITCVV-奇维塔韦基亚/契维塔韦基亚(Civitavecchia)",
  "ITNAP": "ITNAP-那不勒斯(Napoli/ Naples)",
  "ITSPE": "ITSPE-斯佩齐亚(La Spezia)",
  "JMKIN": "JMKIN-金斯敦/金斯顿(Kingston)",
  "JMMBJ": "JMMBJ-蒙特格贝/蒙特歌湾(Montego Bay)",
  "JPHIJ": "JPHIJ-广岛(Hiroshima)",
  "JPKIJ": "JPKIJ-新泻(Niigata)",
  "JPKUH": "JPKUH-钏路(Kushiro)",
  "JPNAH": "JPNAH-那霸/那坝(Naha)",
  "JPSHS": "JPSHS-下关(Shimonoseki)",
  "JPTKY": "JPTKY-德山(Tokuyama)",
  "JPUBJ": "JPUBJ-宇部(Ube)",
  "JPYOK": "JPYOK-横滨(Yokohama)",
  "KPCHO": "KPCHO-清津(Chungjin/ Chongjin)",
  "KRKAN": "KRKAN-光阳(Gwangyang /Kwangyang)",
  "KRUSN": "KRUSN-蔚山(Ulsan)",
  "NOHRY": "NOHRY-喜罗雅(HEROYA)",
  "JPNSR": "JPNSR-能代(NOSHIRO)",
  "QAYID": "QAYID-梅赛伊德(MESAIEED)",
  "AUKUR": "AUKUR-克内尔(KURNELL)",
  "INVIZ": "INVIZ-威扎吉港(VIZAG)",
  "KWL": "KWL-桂林两江国际机场(Guilinliangjiangguojijichang)",
  "LCCAS": "LCCAS-卡斯特里港/卡斯特里/卡斯瑞斯(Castries)",
  "LRCPA": "LRCPA-帕尔马斯角(Cape Palmas)",
  "KITRW": "KITRW-塔拉瓦岛/塔拉瓦(Tarawa)",
  "CACRO": "CACRO-克柔佛顿港(CROFTON)",
  "USPAR": "USPAR-阿瑟港(PORT ARTHUR)",
  "KROKK": "KROKK-玉溪(okgye)",
  "KHSIH": "KHSIH-西哈努克城(SHIANOUKVILLE)",
  "USGEI": "USGEI-盖斯马(GEISMAR)",
  "PVG": "PVG-上海浦东国际机场(Shanghaipudongguojijichang)",
  "AEJDA": "AEJDA-鲁怀斯(JEBEL DHANNA-RUWAIS)",
  "LJG": "LJG-丽江三义国际机场(Lijiang Sanyi International Airport)",
  "CNCJG": "CNCJG-漕泾港(CAOJING)",
  "XIY": "XIY-西安咸阳国际机场(Xianxianyangguojijichang)",
  "IDMAK": "IDMAK-孟加锡(MAKASSAR)",
  "NLBRS": "NLBRS-布雷斯肯斯(BRESKENS)",
  "PAARM": "PAARM-阿穆埃耶斯港(armuelles)",
  "IEFOV": "IEFOV-福因斯/佛尼斯(Foynes)",
  "IELMK": "IELMK-利默里克(Limerick)",
  "IEWAT": "IEWAT-沃特福德(Waterford)",
  "CNAQG": "CNAQG-安庆(Anqing)",
  "CNBIH": "CNBIH-北海(Beihai)",
  "CNBSD": "CNBSD-宝山(Baoshan)",
  "CNCFD": "CNCFD-曹妃甸港",
  "CNCGS": "CNCGS-常熟(Changshu)",
  "CNCHE": "CNCHE-城澳(Chengao)",
  "CNCPI": "CNCPI-常平(Changping)",
  "CNCZX": "CNCZX-常州(Changzhou)",
  "CNDAY": "CNDAY-大亚湾(Dayawan)",
  "CNDCD": "CNDCD-大陈岛(Dachendao)",
  "CNDDP": "CNDDP-地都(Didu)",
  "CNDDW": "CNDDW-东岱湾(Dongdaiwan)",
  "CNDGN": "CNDGN-东港(Donggang)",
  "CNDGP": "CNDGP-东平(Dongping)",
  "CNDJK": "CNDJK-东江口",
  "CNDLD": "CNDLD-大鹿岛(Daludao)",
  "CNDMJ": "CNDMJ-斗门井岸(Doumenjingan)",
  "CNDMY": "CNDMY-大麦屿(Damaiyu)",
  "CNDOU": "CNDOU-斗门(Doumen)",
  "CNDSH": "CNDSH-东石(Dongshi)",
  "CNDSN": "CNDSN-东山(Dongshan)",
  "CNDTU": "CNDTU-洞头(Dongtou)",
  "CNDYG": "CNDYG-东营(Dongying)",
  "CNENP": "CNENP-恩平横板(Enpinghengban)",
  "CNFCH": "CNFCH-凤城(Fengcheng)",
  "CNFUJ": "CNFUJ-富锦(Fujin)",
  "CNFUY": "CNFUY-抚远(Fuyuan)",
  "CNFZH": "CNFZH-福州(Fuzhou)",
  "CNGBG": "CNGBG-关埠港(Guanbugang)",
  "CNGCH": "CNGCH-莞城(Guancheng)",
  "CNGGK": "CNGGK-宫口(Gongkou)",
  "CNGIS": "CNGIS-桂山(Guishan)",
  "CNGOM": "CNGOM-高明(Gaoming)",
  "WUX": "WUX-无锡硕放国际机场(WUXISHUOFANGGUOJIJICHANG)",
  "MXPUC": "MXPUC-波多黎各恰帕斯(PUERTO CHIAPAS)",
  "IDTPP": "IDTPP-丹戎不碌(TANJUNG PRIOK)",
  "MYTLP": "MYTLP-丹绒浪沙港(TANJUNG LANGSAT PORT)",
  "PHGES": "PHGES-桑托斯将军港(GENERAL SANTOS)",
  "USNWJ": "USNWJ-新泽西州(GLOBAL TERMINALS)",
  "INKPI": "INKPI-克里什纳帕特南(KRISHNAPATNAM)",
  "CNGGU": "CNGGU-东莞",
  "RUKZM": "RUKZM-科兹米诺(KOZMINO)",
  "CNGLG": "CNGLG-关累(Guanlei)",
  "IDTIM": "IDTIM-提来卡(TIMIKA)",
  "CNSYM": "CNSYM-思茅(Simao)",
  "THQSG": "THQSG-清盛港(QINGSHENG)",
  "LABXG": "LABXG-班相果(BANXIANGGUO)",
  "LAJMM": "LAJMM-金木棉(JINMUMIAN)",
  "KRTGH": "KRTGH-东海(DONGHAE)",
  "AUPPI": "AUPPI-皮里港(Port Pirie)",
  "AUSYD": "AUSYD-悉尼(Sydney)",
  "AUTSV": "AUTSV-汤斯维尔/敦斯维尔(Townsville)",
  "BAH": "BAH-Muharraq International(Muharraq Internationalf)",
  "BDCHL": "BDCHL-查尔纳港(Chalna Anchorage/ Chalna)",
  "BEANR": "BEANR-安特卫普(Antwerpen)",
  "BEOST": "BEOST-奥斯坦德(Ostend (Oostende))",
  "BHBAH": "BHBAH-巴林(Bahrain)",
  "BHMIN": "BHMIN-米纳苏尔曼/米纳萨门(Mina Sulman)",
  "BMBDA": "BMBDA-汉密尔顿(Hamilton)",
  "BNBWN": "BNBWN-斯里巴加湾港(Bandar Seri Begawan)",
  "BRAJU": "BRAJU-阿拉卡茹/阿腊卡茹(Aracaju)",
  "BRMAO": "BRMAO-马瑙斯(Manaus)",
  "BRMCZ": "BRMCZ-马塞约(Maceio)",
  "NNG": "NNG-南宁吴圩机场(Nanningwuxujichang)",
  "NODRM": "NODRM-德拉门/德腊门(Drammen)",
  "NOHFT": "NOHFT-哈默菲斯特/哈莫弗斯特(Hammerfest)",
  "NOKSU": "NOKSU-克里斯蒂安松(Kristiansund)",
  "NOTON": "NOTON-滕斯贝格/通斯贝格(Tonsberg)",
  "NUALO": "NUALO-阿洛菲(Alofi)",
  "NZCHC": "NZCHC-克赖斯特彻奇(Christchurch)",
  "NZNSN": "NZNSN-纳尔逊(Nelson)",
  "GRRHO": "GRRHO-罗得/罗德斯(Rhodes Island/ Rhodes)",
  "GRSKG": "GRSKG-塞萨洛尼基/萨洛尼亚/萨洛尼卡(Thessaloniki)",
  "GTPRQ": "GTPRQ-夸特扎尔港/库特扎尔(Puerto Quetzal)",
  "GTSTC": "GTSTC-圣托马斯/圣托马斯德卡斯蒂利亚(Puerto Santo Tomas de Castilla)",
  "GYNAM": "GYNAM-新阿姆斯特丹(New Amsterdam)",
  "HFE": "HFE-合肥骆岗机场(Hefeiluogangjichang)",
  "HNSLO": "HNSLO-圣洛伦索(San Lorenzo)",
  "HRB": "HRB-哈尔滨太平国际机场(Harbintaipingguojijichang)",
  "KRCJU": "KRCJU-济州(CHEJU)",
  "USRSF": "USRSF-瑞瑟夫(RESERVE)",
  "IDSKD": "IDSKD-南加里曼丹(SOUTH KALIMANTAN)",
  "USGRH": "USGRH-格雷港(GRAYS HARBOUR)",
  "JPSKI": "JPSKI-境港(SAKAIMINATO)",
  "MYKUN": "MYKUN-库纳克(KUNAK)",
  "PHMAB": "PHMAB-马比尼(MABINA)",
  "SGPAC": "SGPAC-亚逸查湾岛(PULAU AYER CHAWAN)",
  "JPKUD": "JPKUD-下松(KUDAMATSU)",
  "THMTP": "THMTP-麦普塔普特(MAP TA PHUT)",
  "PYVLL": "PYVLL-维拉塔(VILLETA)",
  "BRPMA": "BRPMA-马德拉(PONTA DA MADEIRA)",
  "CNCOZ": "CNCOZ-潮州(Chaozhou)",
  "CNDCB": "CNDCB-大铲湾(Dachanwan)",
  "CNHGG": "CNHGG-红光(Hongguang)",
  "CNHSI": "CNHSI-黄石(Huangshi)",
  "CNHUD": "CNHUD-葫芦岛(Huludao)",
  "CNHXG": "CNHXG-海口新港(Haikouxingang)",
  "CNJDR": "CNJDR-揭东榕江北河曲溪(Jiedongrongjiangbeihequxi)",
  "CNJZU": "CNJZU-九洲(Jiuzhou)",
  "CNLJQ": "CNLJQ-连江前屿(Lianjiangqianyu)",
  "CNLYG": "CNLYG-连云港(Lianyungang)",
  "CNMAA": "CNMAA-马鞍山(Maanshan)",
  "CNMSA": "CNMSA-梅沙(Meisha)",
  "CNNDS": "CNNDS-宁德沙埕(Ningdeshacheng)",
  "CNNZH": "CNNZH-硇洲(Naozhou)",
  "CNPLI": "CNPLI-蓬莱(Penglai)",
  "CNPTS": "CNPTS-莆田三江口(Putiansanjiangkou)",
  "CNRZH": "CNRZH-日照(Rizhao)",
  "CNSEY": "CNSEY-射阳(Sheyang)",
  "CNSHM": "CNSHM-四会马房(Sihuimafang)",
  "CNSJJ": "CNSJJ-石井窖心(Shijingjiaoxin)",
  "CNSPA": "CNSPA-沙扒(Shapa)",
  "CNSUD": "CNSUD-顺德(Shunde)",
  "CNSYA": "CNSYA-三亚(Sanya)",
  "FJLBS": "FJLBS-兰巴萨(Labasa(Lambasa))",
  "FRLRH": "FRLRH-拉罗谢尔/拉罗舍尔(La Rochelle)",
  "FRTLN": "FRTLN-土伦(Toulon)",
  "GACLZ": "GACLZ-洛佩斯角(Cap Lopez)",
  "GAPOG": "GAPOG-谦蒂尔港/让蒂尔港(Port Gentil)",
  "GBCDF": "GBCDF-加的夫(Cardiff)",
  "GBFAL": "GBFAL-法尔茅斯(Falmouth)",
  "GBIMM": "GBIMM-伊明赫姆(Immingham)",
  "GBLON": "GBLON-伦敦(London)",
  "GBMID": "GBMID-米德尔斯伯勒(Middlesbrough)",
  "GBPME": "GBPME-朴次茅斯(Portsmouth)",
  "GBPTB": "GBPTB-塔尔伯特港/塔尔博特港(Port Talbot)",
  "GEBUS": "GEBUS-巴统(Batumi)",
  "GFCAY": "GFCAY-卡宴(Cayenne)",
  "DKFDH": "DKFDH-腓特烈港(Frederikshavn)",
  "DZBJA": "DZBJA-贝贾亚/比加亚(Bejaia (ex Bougie))",
  "DZSKI": "DZSKI-斯基克达/菲利普维尔(Skikda (ex Philippeville))",
  "FIPOR": "FIPOR-波里(Pori (Bjorneborg))",
  "FIVAA": "FIVAA-瓦萨/瓦沙(Vaasa (Vasa))",
  "CNZHH": "CNZHH-庄河(Zhuanghe)",
  "CNZPU": "CNZPU-乍浦(Zhapu)",
  "CNZSM": "CNZSM-漳州石码(Zhangzhoushima)",
  "COBAQ": "COBAQ-巴兰基利亚(Barranquilla)",
  "CTU": "CTU-成都双流国际机场(Chengdushuangliuguojijichang)",
  "CUHAV": "CUHAV-哈瓦那(La Habana)",
  "CUSCS": "CUSCS-南圣克鲁斯/圣克鲁斯蒂尔苏(Santa Cruz del Sur)",
  "USMYG": "USMYG-默特尔格罗夫(MYRTLE GROVE)",
  "AUADL": "AUADL-阿德莱德(Adelaide)",
  "AUBUY": "AUBUY-班伯里/班博里(Bunbury)",
  "AUFRE": "AUFRE-弗里曼特尔(Fremantle)",
  "AUHBA": "AUHBA-霍巴特(Hobart)",
  "AUNTL": "AUNTL-纽卡斯尔(Newcastle)",
  "AUPTJ": "AUPTJ-波特兰(Portland)",
  "AUYAM": "AUYAM-扬皮桑德(Yampi Sound)",
  "AWORJ": "AWORJ-奥拉涅斯塔德/奥腊涅斯塔德(Oranjestad)",
  "BGSOZ": "BGSOZ-索佐波尔/索佐波耳(Sozopol/Sizepoli)",
  "BHY": "BHY-北海福成机场(Beihaifuchengjichang)",
  "BRADR": "BRADR-安格拉杜斯雷斯/安格拉多雷斯(Angra dos Reis)",
  "CKAVA": "CKAVA-阿瓦鲁阿(Avarua)",
  "CLQTV": "CLQTV-金特罗/坤脱罗(Quintero)",
  "CLSVE": "CLSVE-圣文森特/圣维森特港(San Vicente)",
  "CLZAL": "CLZAL-瓦尔迪维亚(Valdivia)",
  "CMVCC": "CMVCC-维多利亚(Victoria)",
  "CNBIC": "CNBIC-北村(Beicun)",
  "CNBLX": "CNBLX-博罗县红海港(Boluoxianhonghaigang)",
  "USDES": "USDES-特斯特汉(DESTREHAN)",
  "IDEKD": "IDEKD-东加里曼丹(EAST KALIMANTAN)",
  "DOCRO": "DOCRO-卡沃罗霍(CABO ROJO)",
  "CNGSH": "CNGSH-高沙(Gaosha)",
  "CNGUG": "CNGUG-贵港(Guigang)",
  "CNHBG": "CNHBG-哈尔滨港(Harbingang)",
  "CNHDG": "CNHDG-花都港(Huadugang)",
  "CNHEK": "CNHEK-黑河(Heihe)",
  "CNHID": "CNHID-惠东港口(Huidonggangkou)",
  "CNHLJ": "CNHLJ-惠来靖海(Huilaijinghai)",
  "CNHME": "CNHME-海门(Haimen)",
  "CNHSC": "CNHSC-韶关新港(Shaoguanxingang)",
  "CNHSN": "CNHSN-鹤山(Heshan)",
  "CNHTG": "CNHTG-荷塘(Hetang)",
  "CNHUH": "CNHUH-黄骅(Huanghua)",
  "CNHUL": "CNHUL-虎林(Hulin)",
  "CNHXD": "CNHXD-黄兴岛(Huangxingdao)",
  "CNHZH": "CNHZH-湖州(Huzhou)",
  "CNJAY": "CNJAY-嘉荫(Jiayin)",
  "CNJIA": "CNJIA-江阴(Jiangyin)",
  "CNJIS": "CNJIS-江山(Jiangshan)",
  "CNJIU": "CNJIU-九江(Jiujiang)",
  "CNJIZ": "CNJIZ-甲子(Jiazi)",
  "CNJMN": "CNJMN-江门(Jiangmen)",
  "CNJMS": "CNJMS-佳木斯港(Jiamusigang)",
  "BRSSO": "BRSSO-圣塞巴斯蒂昂(Sao Sebastiao)",
  "TRF": "TRF-Torf",
  "TRGEL": "TRGEL-盖利博卢(Gelibolu)",
  "PGANB": "PGANB-安诺瓦湾/阿内瓦湾(Anewa Bay)",
  "PGKIE": "PGKIE-基埃塔(Kieta)",
  "PGLAE": "PGLAE-莱城(Lae)",
  "PGMAG": "PGMAG-马当(Madang)",
  "PGRAB": "PGRAB-腊包尔/腊包尔港(Rabaul)",
  "PGWWK": "PGWWK-威瓦克(Wewak)",
  "PHAPR": "PHAPR-阿帕里(Aparri)",
  "PKGWD": "PKGWD-瓜德尔/瓜达尔(Gwadar)",
  "PHLIN": "PHLIN-林加延(Lingayen)",
  "PHMVS": "PHMVS-马里韦莱斯(Mariveles)",
  "PKORW": "PKORW-奥尔马拉/奥尔马腊(Ormara)",
  "PLGDN": "PLGDN-格但斯克(Gdansk)",
  "MPTIQ": "MPTIQ-提尼安岛(Tinian)",
  "BRBTB": "BRBTB-特罗姆柏塔斯(PORTO TROMBETAS)",
  "OMMFH": "OMMFH-费赫勒港(Mina al Fahal)",
  "OMOPQ": "OMOPQ-米纳卡布斯(Mina Qaboos/ Port Qaboos)",
  "OMSLL": "OMSLL-塞拉莱/萨拉拉(Salalah)",
  "PACTB": "PACTB-克里斯托瓦尔/克里斯托巴尔(Cristobal)",
  "PECHM": "PECHM-钦博塔(Chimbote)",
  "PECLL": "PECLL-卡亚俄(Callao)",
  "PAONX": "PAONX-科隆(Colon)",
  "IDAMQ": "IDAMQ-安汶(Ambon)",
  "IDBLW": "IDBLW-勿拉湾(Belawan)",
  "IDDUM": "IDDUM-杜迈(Dumai)",
  "IDKOE": "IDKOE-古邦(Kupang)",
  "IDPNJ": "IDPNJ-潘姜(Panjang)",
  "IDSAT": "IDSAT-桑坦港(Santan Terminal)",
  "IDTAN": "IDTAN-丹戎乌班(Tanjunguban)",
  "IDUPG": "IDUPG-乌戎潘当(Ujung Pandang)",
  "IEDUB": "IEDUB-都柏林(Dublin)",
  "YEMKX": "YEMKX-木卡拉/穆卡拉(Mukalla)",
  "BRTUB": "BRTUB-图巴朗(Tubarao)",
  "BRVIX": "BRVIX-维多利亚(Vitoria)",
  "BSNAS": "BSNAS-拿骚(Nassau)",
  "CACHA": "CACHA-夏洛特敦(Charlottetown)",
  "CACHV": "CACHV-丘吉尔(Churchill)",
  "BZBZE": "BZBZE-伯利兹城(Belize City)",
  "CAGOR": "CAGOR-戈尔德里弗(Gold River)",
  "CAHAL": "CAHAL-哈利法克斯(Halifax)",
  "CAHAM": "CAHAM-哈密尔顿(Hamilton)",
  "CANNO": "CANNO-纳奈莫(Nanaimo)",
  "CAPAB": "CAPAB-艾伯尼港(Port Alberni)",
  "CAPAF": "CAPAF-艾尔夫雷德港(Port-Alfred)",
  "CAPCA": "CAPCA-卡提尔港/卡提亚港(Port-Cartier)",
  "CAPCO": "CAPCO-科尔本港(Port Colborne)",
  "CAPOW": "CAPOW-鲍威尔(Powell River)",
  "CAPRR": "CAPRR-鲁珀特港(Prince Rupert)",
  "CAPTA": "CAPTA-塔西斯(Tahsis)",
  "CAQUE": "CAQUE-魁北克(Quebec)",
  "CASEI": "CASEI-七岛(Sept-Iles)",
  "CASJB": "CASJB-圣约翰(St John)",
  "CASJF": "CASJF-圣约翰斯(St John's)",
  "CASNI": "CASNI-萨尔尼亚(Sarnia)",
  "CASSM": "CASSM-苏圣马丽(Sault Ste Marie)",
  "CATHU": "CATHU-散德湾(Thunder Bay)",
  "CATRR": "CATRR-三河城(Three Rivers/ Trois-Rivieres)",
  "CAYRH": "CAYRH-雅茅思(Yarmouth)",
  "CAMTR": "CAMTR-蒙特利尔(Montreal)",
  "HRSPU": "HRSPU-斯普利特(Split)",
  "HRZAD": "HRZAD-扎达尔(Zadar)",
  "JPKNU": "JPKNU-衣浦(Kinuura)",
  "HNTEA": "HNTEA-特拉(Tela)",
  "HRDBV": "HRDBV-杜布罗夫尼克(Dubrovnik)",
  "HKHKG": "HKHKG-香港(Hong Kong)",
  "TRIST": "TRIST-伊斯坦布尔(Istanbul)",
  "TRKUS": "TRKUS-库沙达瑟(Kusadasi)",
  "TRSIC": "TRSIC-锡诺普(Sinop)",
  "TRTEK": "TRTEK-泰基尔达(Tekirdag)",
  "TRZON": "TRZON-宗古尔达克(Zonguldak)",
  "IDBIT": "IDBIT-比通(Bitung)",
  "IDBPN": "IDBPN-巴厘巴板(Balikpapan)",
  "IDJKT": "IDJKT-雅加达(Jakarta)",
  "IDMDC": "IDMDC-万鸦老(Menado)",
  "IDPLM": "IDPLM-巨港(Palembang)",
  "IDPRO": "IDPRO-普罗博林戈(Probolinggo)",
  "IDSUB": "IDSUB-泗水(Surabaya)",
  "IDTTE": "IDTTE-德那第(Ternate)",
  "IEBYT": "IEBYT-班特里(Bantry)",
  "IEGWY": "IEGWY-戈尔韦/戈尔维(Galway)",
  "IRBND": "IRBND-阿巴斯港(Bandar Abbas)",
  "IRZBR": "IRZBR-恰赫巴哈尔/查赫巴尔(Chah Bahar)",
  "MEKOT": "MEKOT-科托尔(Kotor)",
  "ILAKL": "ILAKL-阿什克伦(Ashkelon)",
  "NZTIU": "NZTIU-蒂马鲁/提马鲁(Timaru)",
  "NZWLG": "NZWLG-惠灵顿(Wellington)",
  "NZWRE": "NZWRE-璜加雷/皇加雷(Whangarei)",
  "NZWSZ": "NZWSZ-韦斯特波特(Westport)",
  "CLHSO": "CLHSO-瓦斯科(Huasco)",
  "CLIQQ": "CLIQQ-伊基克(Iquique)",
  "CLLQN": "CLLQN-利尔奎(Lirquen)",
  "CLANF": "CLANF-安托法加斯塔(Antofagasta)",
  "CLSAI": "CLSAI-圣安东尼奥(San Antonio)",
  "CLTOQ": "CLTOQ-托科皮亚/托科皮利亚(Tocopilla)",
  "CIDAB": "CIDAB-达布(Dabou)",
  "CISPY": "CISPY-圣佩德罗(San-Pedro)",
  "CGPNR": "CGPNR-黑角(Pointe Noire)",
  "CKRAR": "CKRAR-拉罗通加岛(Rarotonga)",
  "CMKBI": "CMKBI-克里比(Kribi)",
  "PNPCN": "PNPCN-皮特凯恩岛(Pitcairn Island)",
  "CNGGZ": "CNGGZ-广州",
  "ZASDB": "ZASDB-萨尔达尼亚湾/萨尔达尼亚港(Saldanha Bay)",
  "KPHUN": "KPHUN-兴南",
  "EGWAF": "EGWAF-wadi feiran",
  "INPNJ": "INPNJ-潘吉姆PANJIM",
  "LULUX": "LULUX-卢森堡(LUXEMBOURG)",
  "VNOSP": "VNOSP-saigon petro oil terminal",
  "AUALI": "AUALI-澳大利亚",
  "THRYG": "THRYG-罗永(RAYONG)",
  "USANG": "USANG-安吉利斯",
  "KRKWA": "KRKWA-KWANG YANG",
  "MYKEL": "MYKEL-KELANG巴生",
  "IDNIT": "IDNIT-BINTUNI",
  "JPKAW": "JPKAW-川崎(KAWASAKI)",
  "IDEKO": "IDEKO-EKOR",
  "VAAAA": "VAAAA-维拉",
  "MYKUA": "MYKUA-关丹(KUANTAN)",
  "ANBON": "ANBON-BONAIRE",
  "INHAL": "INHAL-HALDIA",
  "JPKAR": "JPKAR-唐津",
  "JPICH": "JPICH-市原",
  "IDWAI": "IDWAI-WAISUMO",
  "JPSKT": "JPSKT-SAKATA(酒田)",
  "IDBDJ": "IDBDJ-马辰(BANJARMASIN)",
  "KRTGY": "KRTGY-TONG YOUNG",
  "CAPAL": "CAPAL-阿尔贝尼",
  "VCSVD": "VCSVD-圣文森特",
  "AUGTE": "AUGTE-格鲁特",
  "JPTND": "JPTND-富田",
  "RORZY": "RORZY-摩尔多瓦",
  "JPHTD": "JPHTD-傅多(HAKATA)",
  "IDBUW": "IDBUW-保堡",
  "JPOGS": "JPOGS-扇岛",
  "RUDKA": "RUDKA-德卡斯特瑞",
  "VNPHU": "VNPHU-富美",
  "JPAOJ": "JPAOJ-青森",
  "RUPPN": "RUPPN-普利斯坦",
  "JPSGM": "JPSGM-日本 盐釜",
  "JPTRH": "JPTRH-",
  "JPMBT": "JPMBT-",
  "VEGUT": "VEGUT-GUANTA",
  "IDKOL": "IDKOL-科拉卡",
  "VECRI": "VECRI-CRISTODAL",
  "PHTWT": "PHTWT-塔威",
  "CNCGM": "CNCGM-崇明(Chongming)",
  "AQABA": "AQABA-亚喀巴",
  "PHBCD": "PHBCD-拔科洛德",
  "AEDAS": "AEDAS-达斯岛(DAS ISLAND)",
  "CNCHY": "CNCHY-潮阳(Chaoyang)",
  "TRISK": "TRISK-伊斯肯德伦(Iskenderun)",
  "TRIZM": "TRIZM-伊兹密尔(Izmir)",
  "TRIZT": "TRIZT-伊兹米特(Izmit)",
  "TRMER": "TRMER-梅尔辛(Mersin)",
  "TRSSX": "TRSSX-萨姆松(Samsun)",
  "TRTZX": "TRTZX-特拉布宗/特拉布松(Trabzon)",
  "TTCHA": "TTCHA-查瓜拉马斯/恰瓜拉马斯(Chaguaramas)",
  "IRABD": "IRABD-阿巴丹(Abadan)",
  "IRBUZ": "IRBUZ-布什尔(Bushire/ Bushehr)",
  "IRMRX": "IRMRX-马赫沙赫尔港(Bandar-e Mah Shahr)",
  "IQFAO": "IQFAO-法奥(Fao)",
  "ISISA": "ISISA-伊萨菲厄泽/伊萨菲约杜尔(Isafjordur - hofn)",
  "ISN": "ISN-Sloulin Field International",
  "ITAOI": "ITAOI-安科纳(Ancona)",
  "ITBDS": "ITBDS-布林迪西(Brindisi)",
  "ITBRI": "ITBRI-巴里(Bari)",
  "ITFAL": "ITFAL-法尔科纳拉(Falconara)",
  "ITGEA": "ITGEA-杰拉(Gela)",
  "ITPMO": "ITPMO-巴勒莫(Palermo)",
  "ITPTO": "ITPTO-托雷斯港(Porto Torres)",
  "ITSAL": "ITSAL-萨莱诺(Salerno)",
  "ITTRS": "ITTRS-的里雅斯特(Trieste)",
  "ILTLV": "ILTLV-特拉维夫(Tel-Aviv/ Tel Aviv-Yafo)",
  "IMDGS": "IMDGS-道格拉斯(Douglas)",
  "ILASH": "ILASH-阿什杜德(Ashdod)",
  "ILHFA": "ILHFA-海法(Haifa)",
  "INBHU": "INBHU-包纳加尔(Bhavnagar)",
  "INBOM": "INBOM-孟买(Bombay/ Mumbai)",
  "INC": "INC-银川河东机场(Yinchuanhedongjichang)",
  "INCCU": "INCCU-加尔格答/加尔格达(Calcutta/ Kolkata)",
  "INCOK": "INCOK-科钦(Cochin)",
  "INTUT": "INTUT-杜蒂戈林(Tuticorin)",
  "INIXY": "INIXY-根德拉/坎德拉(Kandla)",
  "INIXZ": "INIXZ-布莱尔港(Port Blair)",
  "INKRK": "INKRK-加里加尔(Karikal/ Karaikal)",
  "INMAA": "INMAA-金奈/马德拉斯(Chennai/Madras)",
  "INMRM": "INMRM-莫尔穆冈(Marmagao (Marmugao))",
  "INMUN": "INMUN-蒙德拉(Mundra)",
  "JPYOS": "JPYOS-横须贺(Yokosuka)",
  "INNML": "INNML-新芒格洛尔(New Mangalore)",
  "INNPT": "INNPT-纳格伯蒂讷姆/纳格帕提南(Nagapattinam)",
  "INNSA": "INNSA-加瓦拉尔?尼赫鲁港(JAWAHARLAL NEHRU)",
  "INPBD": "INPBD-博尔本德尔(Porbandar)",
  "INPRT": "INPRT-巴拉迪布/帕拉迪布(Paradip/ Paradip Garh)",
  "INRED": "INRED-雷迪/来里港/雷迪港(Redi)",
  "JOAQJ": "JOAQJ-亚喀巴(Aqaba/ Al'Aqabah)",
  "JPAXT": "JPAXT-秋田(Akita)",
  "JPFKY": "JPFKY-福山(Fukuyama)",
  "JPHIM": "JPHIM-姬路(Himeji)",
  "JPHTC": "JPHTC-日立(Hitachi)",
  "JPKNZ": "JPKNZ-金泽(Kanazawa)",
  "JPKZU": "JPKZU-木更津(Kisarazu)",
  "JPNGS": "JPNGS-长崎(Nagasaki)",
  "JPOTR": "JPOTR-小樽(Otaru)",
  "JPTAK": "JPTAK-高松(Takamatsu)",
  "JPTYO": "JPTYO-东京(Tokyo)",
  "JPUKB": "JPUKB-神户(Kobe)",
  "NOTOS": "NOTOS-特罗姆瑟(Tromso)",
  "NRINU": "NRINU-瑙鲁岛(Nauru Island)",
  "NTE": "NTE-Nantes-Chateau Bougon",
  "NWA": "NWA-Moheli",
  "NZAKL": "NZAKL-奥克兰(Auckland)",
  "NZDUD": "NZDUD-达尼丁(Dunedin)",
  "NZNPL": "NZNPL-新普利茅斯(New Plymouth)",
  "NZPCN": "NZPCN-皮克顿(Picton)",
  "GRU": "GRU-瓜如尔赫斯国际机场",
  "NZCAS": "NZCAS-查默斯(chalmers)",
  "CNSDG": "CNSDG-水东(SHUIDONG)",
  "CNJOK": "CNJOK-窖口(Jiaokou)",
  "CNJUJ": "CNJUJ-九江(Jiujiang)",
  "CNKZG": "CNKZG-康州港(Kangzhougang)",
  "CNLHD": "CNLHD-绿华岛(Luhuadao)",
  "CNLJY": "CNLJY-廉江营仔(Lianjiangyingzai)",
  "CNLUD": "CNLUD-六都(Liudu)",
  "CNLUZ": "CNLUZ-泸州(Luzhou)",
  "CNLZH": "CNLZH-柳州(Liuzhou)",
  "CNMAC": "CNMAC-马村(Macun)",
  "CNMLI": "CNMLI-梅林(Meilin)",
  "CNMWN": "CNMWN-妈湾(Mawan)",
  "CNNBO": "CNNBO-宁波(Ningbo)",
  "CNNIG": "CNNIG-南宁港(Nanninggang)",
  "CNNKL": "CNNKL-牛牯岭(Niuguling)",
  "CNNUD": "CNNUD-女岛(Nudao)",
  "CNPHB": "CNPHB-平海碧甲(Pinghaibijia)",
  "CNPUT": "CNPUT-莆田(Putian)",
  "CNQGS": "CNQGS-青石(Qingshi)",
  "CNQGY": "CNQGY-清远(Qingyuan)",
  "CNQZC": "CNQZC-泉州崇武(Quanzhouchongwu)",
  "CNROH": "CNROH-饶河(Raohe)",
  "CNROQ": "CNROQ-容奇(Rongqi)",
  "CNSGJ": "CNSGJ-松江(Songjiang)",
  "CNSHK": "CNSHK-蛇口(Shekou)",
  "CNSHQ": "CNSHQ-石歧(Shiqi)",
  "CNSIJ": "CNSIJ-石井(Shijing)",
  "CNSJQ": "CNSJQ-三水(Sanshui)",
  "CNSJU": "CNSJU-石臼(Shijiu)",
  "CNSNS": "CNSNS-三沙(Sansha)",
  "CNSTB": "CNSTB-石头埠(Shitoubu)",
  "CNSWE": "CNSWE-汕尾(Shanwei)",
  "CNSYC": "CNSYC-沙鱼涌(Shayuchong)",
  "CNTAC": "CNTAC-太仓(Taicang)",
  "FJLTK": "FJLTK-劳托卡(Lautoka)",
  "FJSUV": "FJSUV-苏瓦(Suva)",
  "FMTKK": "FMTKK-特鲁克群岛(Chuuk (ex Truk))",
  "FMYAP": "FMYAP-雅浦(Yap)",
  "FOVES": "FOVES-韦斯特门港(Vestmanhavn)",
  "FRBAY": "FRBAY-巴约讷/巴荣讷(Bayonne)",
  "FRBIA": "FRBIA-巴斯蒂亚(Bastia)",
  "FRCER": "FRCER-瑟堡(Cherbourg)",
  "FRCFR": "FRCFR-卡昂/冈城(Caen)",
  "FRCQF": "FRCQF-加来(Calais)",
  "FRD": "FRD-Friday Harbor Airport",
  "FRDPE": "FRDPE-迪耶普/第耶普(Dieppe)",
  "FRLAV": "FRLAV-拉瓦拉/拉维拉(Lavera)",
  "FRLCT": "FRLCT-拉西约塔/拉西奥塔(La Ciotat)",
  "FRLEH": "FRLEH-勒阿弗尔(Le Havre)",
  "FRLRT": "FRLRT-洛里昂(Lorient)",
  "FRNCE": "FRNCE-尼斯(Nice)",
  "FRSET": "FRSET-塞特(Sete)",
  "FRSNR": "FRSNR-圣纳泽尔(St Nazaire)",
  "FRURO": "FRURO-鲁昂(Rouen)",
  "GAOWE": "GAOWE-奥文多(Owendo)",
  "MMAKY": "MMAKY-实兑(Akyab(Sittwe))",
  "MMBSX": "MMBSX-勃生(Bassein)",
  "MMH": "MMH-Mammoth Lakes Airport",
  "MMSAN": "MMSAN-山多威(Sandoway/Thandwe)",
  "MMXYE": "MMXYE-耶城(Ye)",
  "GFQKR": "GFQKR-库鲁(Kourou)",
  "GMBJL": "GMBJL-班珠尔(Banjul)",
  "GNCKY": "GNCKY-科纳克里(Conakry)",
  "GHTEM": "GHTEM-特马(Tema)",
  "GHWEA": "GHWEA-温尼巴(Winneba)",
  "PHZAM": "PHZAM-三宝颜(Zamboanga)",
  "PGKIM": "PGKIM-金贝/基姆贝(Kimbe)",
  "GPBBR": "GPBBR-巴斯特尔(Basse-Terre)",
  "GQBSG": "GQBSG-巴塔(Bata)",
  "GQSSG": "GQSSG-马拉博(Malabo)",
  "GRGPA": "GRGPA-佩特雷/帕特瑞(Patras)",
  "GRITA": "GRITA-伊泰阿(Itea)",
  "GRJKH": "GRJKH-希俄斯(Chios)",
  "GRKLX": "GRKLX-卡拉迈/卡拉梅塔(Kalamata)",
  "GRMGR": "GRMGR-迈加拉(Megara)",
  "LRUCN": "LRUCN-布坎南(Buchanan)",
  "LTKLJ": "LTKLJ-克莱佩达(Klaipeda)",
  "LVLPX": "LVLPX-利耶帕亚(Liepaja)",
  "LVRIX": "LVRIX-里加(Riga)",
  "LVVNT": "LVVNT-文茨皮尔斯(Ventspils)",
  "LYBEN": "LYBEN-班加西(Bingazi (Benghazi))",
  "LYDRX": "LYDRX-德尔纳(Darnah)",
  "LYESI": "LYESI-锡德尔/西德尔/伊赛德(As Sidr)",
  "LYLMQ": "LYLMQ-马萨勃利加/卜雷加港(Marsa Brega)",
  "LYMHR": "LYMHR-哈里盖港(Marsa el Hariga)",
  "LYMRA": "LYMRA-米苏拉塔区/米苏腊塔(Misurata)",
  "LYTIP": "LYTIP-的黎波里(Tripoli)",
  "LYZUE": "LYZUE-祖埃提纳(Zueitina)",
  "MAAGA": "MAAGA-阿加迪尔(Agadir)",
  "MACAS": "MACAS-卡萨布兰卡(Casablanca)",
  "LYRLA": "LYRLA-拉斯拉努夫(Ras Lanuf)",
  "MCMCM": "MCMCM-蒙特卡洛(Monte-Carlo/ Monte Carlo)",
  "MARBA": "MARBA-拉巴特(Rabat)",
  "MASFI": "MASFI-萨菲(Safi)",
  "MATTU": "MATTU-得土安(Tetouan)",
  "MEBAR": "MEBAR-巴尔(Bar)",
  "MGFTU": "MGFTU-多凡堡(Fort Dauphin (Toalagnaro))",
  "MGMJN": "MGMJN-马任加(Majunga (Mahajanga))",
  "MGQ": "MGQ-Mogadishu",
  "MGTLE": "MGTLE-图莱亚尔(Tulear (Toliara))",
  "MHTAR": "MHTAR-Taroa",
  "PKKHI": "PKKHI-卡拉奇(Karachi)",
  "PKPSI": "PKPSI-伯斯尼(Pasni)",
  "MPSPN": "MPSPN-塞班岛(Saipan)",
  "PLSZZ": "PLSZZ-什切青(Szczecin)",
  "CNQBS": "CNQBS-青保税港",
  "RUSVE": "RUSVE-斯维特拉",
  "UAYUZ": "UAYUZ-尤日内(YUZHNYY)",
  "AUBEL": "AUBEL-贝尔湾",
  "THKSI": "THKSI-科西昌",
  "VNVUT": "VNVUT-头顿(Vung Tau)",
  "USLOG": "USLOG-朗维尤(longview)",
  "JPIMI": "JPIMI-IMARI",
  "BRSPB": "BRSPB-伊塔瓜伊",
  "USABR": "USABR-阿伯丁",
  "CNTNJ": "CNTNJ-天津港",
  "AUQDN": "AUQDN-埃登",
  "IDKDW": "IDKDW-肯达旺",
  "KRTJI": "KRTJI-唐津",
  "KRJGE": "KRJGE-巨济",
  "IDOBI": "IDOBI-奥比岛",
  "JPMIZ": "JPMIZ-水岛(MIZUSHIMA)",
  "IDMKQ": "IDMKQ-梅克奇",
  "AUSPB": "AUSPB-斯普林湾",
  "JPKAE": "JPKAE-鹿岛",
  "USQPD": "USQPD-POLAND",
  "CNSNZ": "CNSNZ-深圳",
  "ILEIL": "ILEIL-EILAT",
  "USAC3": "USAC3-东南太平洋",
  "JPTOY": "JPTOY-富山",
  "KRCHG": "KRCHG-长项",
  "CNBYQ": "CNBYQ-鲅鱼圈",
  "KPCJN": "KPCJN-清津",
  "PHISL": "PHISL-ISABEL",
  "JPSKD": "JPSKD-板初",
  "THIYG": "THIYG-IAYONG",
  "JPHKT": "JPHKT-博多(FUKUOKA)",
  "JPIYM": "JPIYM-伊予三岛(IYOMISHIMA)",
  "DIKSON": "DIKSON-迪克森",
  "AUWYD": "AUWYD-WYNDHAM",
  "PHRTB": "PHRTB-图巴",
  "JPSMA": "JPSMA-饰磨",
  "JPYWT": "JPYWT-YAWATA",
  "INKAK": "INKAK-KAKINADA",
  "BRSAN": "BRSAN-桑塔纳",
  "JPKND": "JPKND-KANDA",
  "JPTTJ": "JPTTJ-鸟取",
  "GRAND": "GRAND-ANDROS",
  "UANLV": "UANLV-尼古拉伊夫(NIKOLAEV)",
  "JPAIO": "JPAIO-相生",
  "JPKWS": "JPKWS-川崎(KAWASAKI)",
  "JPAMA": "JPAMA-尼崎",
  "IDTAR": "IDTAR-台军(TRAJUN)",
  "JPMAI": "JPMAI-舞鹤",
  "JPFNB": "JPFNB-船桥(FUNABASHI)",
  "MNULN": "MNULN-乌兰巴托",
  "CNNYM": "CNNYM-南油码头",
  "CNMMG": "CNMMG-茂名港",
  "PHPLW": "PHPLW-PALAWAN巴拉望",
  "USOTS": "USOTS-阿纳科尔特斯",
  "IDTPN": "IDTPN-巴库(TANJUNG PEMANCINGAN)",
  "JPISI": "JPISI-石狩",
  "USDVT": "USDVT-达旺特(DAVANT)",
  "JPSDJ": "JPSDJ-仙台",
  "USKAL": "USKAL-卡拉马(KALAMA)",
  "VNCPH": "VNCPH-津浦",
  "RURDP": "RURDP-鲁德纳亚",
  "JPTOM": "JPTOM-",
  "PHBUL": "PHBUL-布兰",
  "USTAZ": "USTAZ-阿瑟港",
  "PHMAR": "PHMAR-MAC ARTHUR",
  "USATR": "USATR-阿瑟",
  "JPMKK": "JPMKK-MAKURAZAKI",
  "KRCHF": "KRCHF-镇海",
  "KRBPG": "KRBPG-北坪",
  "PHPOT": "PHPOT-PORO POINT",
  "VNPCA": "VNPCA-锦普港(PORT CAMPHA)",
  "CLCRL": "CLCRL-科拉尔",
  "IDMOT": "IDMOT-MOTUI",
  "IDSBK": "IDSBK-塞布库",
  "ECLLD": "ECLLD-拉利伯塔德",
  "IDSIQ": "IDSIQ-",
  "IDSZH": "IDSZH-赛尼帕",
  "KPKAN": "KPKAN-松关港",
  "SUBIC": "SUBIC-苏比克",
  "INKRI": "INKRI-科里什纳帕特南",
  "JPIHA": "JPIHA-新居滨",
  "DELEE": "DELEE-莱尔",
  "VUSAN": "VUSAN-圣吐(Santo)",
  "KRDAE": "KRDAE-台普",
  "JPUWJ": "JPUWJ-UWAJIMA宇和岛",
  "JPSMS": "JPSMS-SHIMONOSEKI下关",
  "INJGD": "INJGD-齐格尔堡港",
  "JPKIS": "JPKIS-君津(KIMITSU)",
  "JPGAM": "JPGAM-蒲郡",
  "IDNNX": "IDNNX-努努坎",
  "MYPKE": "MYPKE-巴生(PORT KELANG)",
  "CNDAL": "CNDAL-大连",
  "VNCLN": "VNCLN-蔡兰",
  "KRJHE": "KRJHE-金海",
  "BRATU": "BRATU-阿拉图(ARATU)",
  "IDMOR": "IDMOR-莫罗瓦利(MOROWALI)",
  "OPSEA": "OPSEA-公海(OPSEA)",
  "YNY": "YNY-襄阳(YANGYANG)",
  "AUKBL": "AUKBL-肯布拉(KEMBLA)",
  "AOKZB": "AOKZB-吉宗巴(KIZOMBA)",
  "ARSLZ": "ARSLZ-圣洛伦索(SAN LORENZO)",
  "SARAB": "SARAB-沙特拉比格(RABIGH)",
  "MSPLY": "MSPLY-普利茅斯(Plymouth)",
  "MQFDF": "MQFDF-法兰西堡(Fort-de-France)",
  "MRNDB": "MRNDB-努瓦迪布(Nouadhibou)",
  "MRNKC": "MRNKC-努瓦克肖特(Nouakchott)",
  "MYJOH": "MYJOH-柔佛(JOHOR)",
  "MTMAR": "MTMAR-马尔萨什洛克(Marsaxlokk)",
  "MTMLA": "MTMLA-瓦莱塔(Malta (Valetta))",
  "INOKH": "INOKH-奥卡港(Okha)",
  "AUONS": "AUONS-翁斯洛(ONSLOW)",
  "VNHON": "VNHON-鸿基(Hongay/ Hongai)",
  "CNTSG": "CNTSG-台山公益(Taishangongyi)",
  "CNXGA": "CNXGA-新港(Xingang)",
  "CNXUK": "CNXUK-逊克(Xunke)",
  "CNYSA": "CNYSA-洋山(Yangshan)",
  "CNCHQ": "CNCHQ-重庆港(Chongqinggang)",
  "CNDJT": "CNDJT-东角头(Dongjiaotou)",
  "CNGAO": "CNGAO-高港(Gaogang)",
  "CNHUA": "CNHUA-黄埔(Huangpuwaimaocangku)",
  "CNJNZ": "CNJNZ-锦州(Jinzhou)",
  "CNMAW": "CNMAW-马尾(Mawei)",
  "CNNTG": "CNNTG-南通(Nantong)",
  "CNSIK": "CNSIK-水口(Shuikou)",
  "CNDAS": "CNDAS-大石化港",
  "CNXHM": "CNXHM-霞海码头",
  "PHLMY": "PHLMY-利迈(LIMAY)",
  "CAHMC": "CAHMC-哈马克(HARMAC)",
  "AER": "AER-索契(SOCHI)",
  "USNFK": "USNFK-诺福克(NORFOLK)",
  "AUPER": "AUPER-珀斯(PERTH)",
  "JPMTZ": "JPMTZ-松坂(MATSUZAKA)",
  "IDCIG": "IDCIG-芝格丁(CIGADING)",
  "AZBAK": "AZBAK-巴库(BAKU)",
  "DZDJE": "DZDJE-杰恩杰恩(Djen-Djen)",
  "BRARB": "BRARB-阿拉图(ARATU)",
  "AUWAL": "AUWAL-沃拉鲁(WALLAROO)",
  "NOMAY": "NOMAY-马洛伊(MAALOY)",
  "JPKAI": "JPKAI-海南(KAINAN)",
  "LKCMB": "LKCMB-科伦坡(Colombo)",
  "LKTAL": "LKTAL-塔莱曼纳尔(Talaimannar)",
  "LKMAN": "LKMAN-马纳尔(Mannar)",
  "DKEBJ": "DKEBJ-埃斯比约/埃斯堡(Esbjerg)",
  "DKFRC": "DKFRC-腓特烈西亚(Fredericia)",
  "DKKAL": "DKKAL-凯隆堡(Kalundborg)",
  "DKODE": "DKODE-欧登塞(Odense)",
  "DMRSU": "DMRSU-罗索(Roseau)",
  "DOHAI": "DOHAI-海纳(Rio Haina)",
  "DOBRX": "DOBRX-巴拉奥纳(Barahona)",
  "DOLRM": "DOLRM-拉罗马纳(La Romana)",
  "DOPOP": "DOPOP-普拉塔港(Puerto Plata)",
  "DOSDQ": "DOSDQ-圣多明各(Santo Domingo)",
  "DZAAE": "DZAAE-安纳巴(Annaba (ex Bone))",
  "DZAZW": "DZAZW-阿尔泽(Arzew)",
  "DZDJI": "DZDJI-吉杰利/季杰利(Djidjelli/Jijel)",
  "DZTEN": "DZTEN-提奈斯/特内斯(Tenes)",
  "EEPRN": "EEPRN-派尔努/皮亚尔努(Parnu)",
  "EGAZA": "EGAZA-阿布宰尼迈/阿布扎尼马(Abu Zenimah)",
  "EGSGA": "EGSGA-萨法贾/萨法贾港(Safaga)",
  "KNBAS": "KNBAS-巴斯特尔(Basseterre)",
  "KPHAE": "KPHAE-海州(Haeju)",
  "KPNAM": "KPNAM-南浦(Nampo)",
  "KMYVA": "KMYVA-莫罗尼(Moroni)",
  "KPWON": "KPWON-元山(Wonsan)",
  "KRKPO": "KRKPO-浦项(Pohang)",
  "KRKUV": "KRKUV-群山(Kunsan/ Gunsan)",
  "KRMOK": "KRMOK-木浦(Mokpo)",
  "KRPUS": "KRPUS-釜山(Busan)",
  "KWKWI": "KWKWI-科威特(Kuwait)",
  "KWMEA": "KWMEA-米纳艾哈迈迪(Mena al Ahmadi/ Mina' al Ahmadi)",
  "KWSAA": "KWSAA-舒艾拜(Shuaiba)",
  "KYGEC": "KYGEC-乔治敦(Georgetown)",
  "LBBEY": "LBBEY-贝鲁特(Beirut)",
  "LBSUR": "LBSUR-苏尔(Sour/ Sur (Tyre))",
  "KHPNH": "KHPNH-金边(Phnom-Penh/ Phnom Penh)",
  "PEPIO": "PEPIO-皮斯科(Pisco)",
  "KEMBA": "KEMBA-蒙巴萨(Mombasa)",
  "PESUP": "PESUP-苏佩/苏普(Supe)",
  "PHILO": "PHILO-伊洛伊洛(Iloilo)",
  "PHLGP": "PHLGP-黎牙实比(Legaspi)",
  "RUSAK": "RUSAK-亚历山大罗夫斯克(Alexandrovsk/ Aleksandrovsk-Sakhalinskiy)",
  "RUUGL": "RUUGL-乌格里哥斯克(Uglegorsk)",
  "RUVNN": "RUVNN-瓦尼诺(Vanino)",
  "RUVVO": "RUVVO-符拉迪沃斯托克/海参崴(Vladivostok)",
  "SLBTE": "SLBTE-邦特(Bonthe)",
  "TCGDT": "TCGDT-大特克(Grand Turk Island)",
  "SAJED": "SAJED-吉达(Jeddah)",
  "SAJUT": "SAJUT-朱阿马码头/朱爱马(Juaymah Terminal)",
  "SAN": "SAN-Lindbergh International Airport",
  "SARTA": "SARTA-拉斯坦努拉/腊斯塔努腊(Ras Tanura)",
  "RELPT": "RELPT-勒波尔(Le Port)",
  "REPDG": "REPDG-加勒茨角/蒂斯格勒特斯(Port de Pointe des Galets)",
  "SBRIN": "SBRIN-林吉科弗(Ringgi Cove)",
  "SIKOP": "SIKOP-科佩尔(Koper)",
  "SCPOV": "SCPOV-维多利亚港(Port Victoria)",
  "SEFAG": "SEFAG-法尔肯贝里/法尔肯贝里耶(Falkenberg)",
  "SEHEL": "SEHEL-赫尔辛堡(Helsingborg)",
  "SEHND": "SEHND-赫纳散德/海诺桑德/赫讷散德(Harnosand)",
  "SDPZU": "SDPZU-苏丹港(Port Sudan)",
  "SEKLR": "SEKLR-卡尔马(Kalmar)",
  "SENRK": "SENRK-诺尔雪平(Norrkoping)",
  "SESDL": "SESDL-松兹瓦尔(Sundsvall)",
  "SEUDD": "SEUDD-乌德瓦拉(Uddevalla)",
  "THLCH": "THLCH-林查班(Laem Chabang)",
  "THPAN": "THPAN-北大年(Pattani)",
  "PYASU": "PYASU-亚松森(ASUNCION)",
  "ERASA": "ERASA-阿萨布/伊萨布(Assab)",
  "ESACE": "ESACE-阿雷西费(Arrecife de Lanzarote)",
  "ESAVS": "ESAVS-阿维莱斯(Aviles)",
  "ESCAD": "ESCAD-加的斯(Cadiz)",
  "ESCEU": "ESCEU-休达(Ceuta)",
  "ECGYE": "ECGYE-瓜亚基尔(Guayaquil)",
  "ESFRO": "ESFRO-费罗尔(Ferrol)",
  "ESLEI": "ESLEI-阿尔梅里亚(Almeria)",
  "ESMLN": "ESMLN-梅利利亚(Melilla)",
  "ESROT": "ESROT-罗塔(Rota)",
  "ESSAG": "ESSAG-萨贡托(Sagunto)",
  "ESTAR": "ESTAR-塔拉戈纳(Tarragona)",
  "BRTRM": "BRTRM-特拉曼达伊(Tramandai)",
  "PRMAZ": "PRMAZ-马亚圭斯(Mayaguez)",
  "PRSJU": "PRSJU-圣胡安(San Juan)",
  "PTFNC": "PTFNC-丰沙尔(Funchal)",
  "PTHOR": "PTHOR-奥尔塔(Horta)",
  "PTLEI": "PTLEI-雷克索斯/莱肖埃斯(Leixoes)",
  "PTPDL": "PTPDL-蓬塔德尔加达港/迪尔格达(Ponta Delgada)",
  "TWKEL": "TWKEL-基隆(Keelung/Chilung/Jilong)",
  "TWKHH": "TWKHH-高雄(Kaohsiung)",
  "TWTPE": "TWTPE-台北(Taipei)",
  "TXK": "TXK-Municipal",
  "TXN": "TXN-黄山屯溪机场(Huangshantunxijichang)",
  "TYS": "TYS-Mcghee Tyson",
  "TZDAR": "TZDAR-达累斯萨拉姆(Dar es Salaam)",
  "TZMYW": "TZMYW-姆特瓦拉(Mtwara)",
  "TZTGT": "TZTGT-坦噶(Tanga)",
  "UAERD": "UAERD-别尔迪扬斯克(Berdiansk/ Berdyansk)",
  "UAIZM": "UAIZM-伊兹梅尔(Izmail)",
  "UAK": "UAK-Narssarssuaq",
  "UAKHE": "UAKHE-赫尔松(Kherson)",
  "UANIK": "UANIK-尼古拉耶夫(Nikolayev)",
  "UAODS": "UAODS-敖德萨(Odessa)",
  "UASVP": "UASVP-塞瓦斯托波尔(Sevastopol)",
  "UAYAL": "UAYAL-雅尔塔(Yalta)",
  "SNDKR": "SNDKR-达喀尔(Dakar)",
  "SNKLC": "SNKLC-考拉克(Kaolack)",
  "SLFNA": "SLFNA-弗里敦(Freetown)",
  "SLPEP": "SLPEP-佩佩尔(Pepel)",
  "SNXLS": "SNXLS-圣路易(St Louis)",
  "SNZIG": "SNZIG-济金绍尔(Ziguinchor)",
  "SOBBO": "SOBBO-柏培拉/博博拉(Berbera)",
  "SOKMU": "SOKMU-基斯马尤(Kismayu)",
  "SOMGQ": "SOMGQ-摩加迪沙(Mogadishu)",
  "SRMOJ": "SRMOJ-蒙戈/蒙格(Moengo)",
  "SRPBM": "SRPBM-帕拉马里博(Paramaribo)",
  "SRPRM": "SRPRM-帕拉南(Paranam)",
  "TWHUN": "TWHUN-花莲(Hualien/Hualian)",
  "TWSUO": "TWSUO-苏澳(Suao)",
  "TWTNN": "TWTNN-台南(Tainan)",
  "TWTXG": "TWTXG-台中(Taichung/Taizhong)",
  "TVFUN": "TVFUN-富纳富提(Funafuti)",
  "TZLDI": "TZLDI-林迪(Lindi)",
  "TZZNZ": "TZZNZ-桑给巴尔岛(Zanzibar)",
  "UAKEH": "UAKEH-刻赤(Kertch)",
  "UAMPW": "UAMPW-马里乌波尔（日丹诺夫）(Mariupol /Zhdanov)",
  "USALB": "USALB-奥尔巴尼(Albany)",
  "USBAL": "USBAL-巴尔的摩(Baltimore)",
  "USCHI": "USCHI-芝加哥(Chicago)",
  "USCHS": "USCHS-查尔斯顿(Charleston)",
  "USDST": "USDST-Adamston",
  "USDUT": "USDUT-荷兰港(Dutch Harbor)",
  "USLAX": "USLAX-洛杉矶(Los Angeles)",
  "USLGB": "USLGB-长滩(Long Beach)",
  "USMOB": "USMOB-莫比尔(Mobile)",
  "USORF": "USORF-诺福克(Norfolk)",
  "USPHL": "USPHL-费城(Philadelphia)",
  "USSEW": "USSEW-苏厄德(Seward)",
  "USSSI": "USSSI-不伦瑞克(Brunswick)",
  "USTOL": "USTOL-托莱多(Toledo)",
  "UYMVD": "UYMVD-蒙得维的亚(Montevideo)",
  "MZMZQ": "MZMZQ-莫桑比克(Mocambique)",
  "VCKTN": "VCKTN-金斯敦(Kingstown)",
  "VELAG": "VELAG-拉瓜伊拉(La Guaira)",
  "VEMAR": "VEMAR-马拉开波(Maracaibo)",
  "VEPPD": "VEPPD-蓬塔?德彼得拉斯(Punta de Piedra)",
  "IDBAT": "IDBAT-巴淡岛(BATAM)",
  "SGPBU": "SGPBU-普劳布科姆(PULAU BUKOM)",
  "USASA": "USASA-阿斯托利亚(ASTORIA)",
  "PHIBL": "PHIBL-伊莎贝尔(ISABEL)",
  "NALUD": "NALUD-卢德立次/鲁得立茨/吕得立茨(Luderitz)",
  "NCNOU": "NCNOU-努美阿(Noumea)",
  "DENOR": "DENOR-诺登哈姆(NORDENHAM)",
  "MXCOA": "MXCOA-夸察夸尔科斯(Coatzacoalcos)",
  "MXGYM": "MXGYM-瓜伊马斯(Guaymas)",
  "MXL": "MXL-Rodolfo Sanchez Taboada",
  "MXMZT": "MXMZT-马萨特兰(Mazatlan)",
  "MXPMD": "MXPMD-马德罗港(Puerto Madero)",
  "MXSRL": "MXSRL-圣罗萨利亚(Santa Rosalia)",
  "MXVER": "MXVER-韦拉克鲁斯(Veracruz)",
  "MYBKI": "MYBKI-哥打基纳巴卢(Kota Kinabalu)",
  "MYJHB": "MYJHB-新山(Johore Bahru)",
  "MYKUD": "MYKUD-古达(Kudat)",
  "MYMKZ": "MYMKZ-马六甲(Malacca)",
  "MYPEN": "MYPEN-槟城(Penang(Georgetown))",
  "MYPKG": "MYPKG-巴生港(Port Kelang)",
  "MYSBW": "MYSBW-诗巫(Sibu)",
  "MYSDK": "MYSDK-山打根(Sandakan)",
  "MYV": "MYV-Marysville",
  "MZINH": "MZINH-伊尼扬巴内/伊尼亚巴内(Inhambane)",
  "MZMNC": "MZMNC-纳卡拉(Nacala)",
  "NFNLK": "NFNLK-金斯敦/诺福克岛(Norfolk Island/ Kingston)",
  "NGBON": "NGBON-邦尼/博尼(Bonny)",
  "NGFOR": "NGFOR-福卡多斯(Forcados)",
  "NGWAR": "NGWAR-瓦里(Warri)",
  "NICIO": "NICIO-科林托(Corinto)",
  "NLAMS": "NLAMS-阿姆斯特丹(Amsterdam)",
  "NLRTM": "NLRTM-鹿特丹(Rotterdam)",
  "NLVLA": "NLVLA-弗拉尔丁恩(Vlaardingen)",
  "NOARE": "NOARE-阿伦达尔(Arendal)",
  "NOBGO": "NOBGO-卑尔根(Bergen)",
  "NOHAU": "NOHAU-海尔格松/豪格松(Haugesund)",
  "NOLAR": "NOLAR-拉尔维克(Larvik)",
  "NOMOL": "NOMOL-莫尔德(Molde)",
  "NONVK": "NONVK-纳尔维克(Narvik)",
  "TGLFW": "TGLFW-洛美(Lome)",
  "STTMS": "STTMS-圣多美(Sao Tome Island)",
  "THBKK": "THBKK-曼谷(Bangkok)",
  "THHKT": "THHKT-普吉(Phuket)",
  "THSAT": "THSAT-梭桃邑(Sattahip)",
  "THSIR": "THSIR-是拉差(Siracha/ Si Racha)",
  "SYBAN": "SYBAN-巴尼亚斯(Banias/ Baniyas)",
  "SYLTK": "SYLTK-拉塔基亚(Lattakia/ Latakia)",
  "SVLLD": "SVLLD-拉利贝塔德(La Libertad)",
  "TNLSK": "TNLSK-拉斯基拉/斯希腊(La Skhirra)",
  "TONEI": "TONEI-内亚富/尼亚夫(Neiafu)",
  "TRAYT": "TRAYT-安塔利亚(Antalya)",
  "TRERE": "TRERE-埃雷利(Eregli)",
  "GRJSY": "GRJSY-锡罗斯(Syros (Syra)/ Siros)",
  "GRKVA": "GRKVA-卡瓦拉(Kavalla/ Kavala)",
  "GRMJT": "GRMJT-米提林尼/米提利尼(Mitylene)",
  "GRPIR": "GRPIR-比雷埃夫斯(Piraeus)",
  "LRMLW": "LRMLW-蒙罗维亚(Monrovia)",
  "LYTOB": "LYTOB-图卜鲁格/托布鲁克(Tobruk)",
  "GPPTP": "GPPTP-皮特尔角城/皮特瑞角(Pointe-a-Pitre)",
  "GRB": "GRB-Austin/Straybel Field",
  "GRHER": "GRHER-伊拉克利翁/基腊克林(Iraklion(Heraklion))",
  "GHCCT": "GHCCT-海岸角(Cape Coast)",
  "GLJSU": "GLJSU-苏克托彭(Maniitsoq (Sukkertoppen))",
  "GIGIB": "GIGIB-直布罗陀(Gibraltar)",
  "MAEUN": "MAEUN-欧云/阿尤恩(Laayoune)",
  "MCMON": "MCMON-摩纳哥(Monaco)",
  "MAMOH": "MAMOH-穆罕默迪耶(Mohammedia)",
  "MANNA": "MANNA-盖尼特拉(Kenitra (ex Port Lyautey))",
  "MATNG": "MATNG-丹吉尔(Tangier)",
  "TLDIL": "TLDIL-帝力(Dili)",
  "TNBIZ": "TNBIZ-比塞大/比泽特(Bizerte/Bizerta)",
  "TNGAE": "TNGAE-加贝斯(Gabes)",
  "THSRI": "THSRI-斯瑞拉察(Sriracha)",
  "TRBDM": "TRBDM-班德尔马(Bandirma)",
  "TRCKZ": "TRCKZ-恰纳卡莱(Canakkale)",
  "TRDRC": "TRDRC-代林杰(Derince)",
  "TNSFA": "TNSFA-斯法克斯(Sfax)",
  "TNTUN": "TNTUN-突尼斯(Tunis)",
  "TRGEM": "TRGEM-盖姆利克(Gemlik)",
  "VNCMT": "VNCMT-蔡美普国际码头(Vncmt)",
  "BRPOR": "BRPOR-PORTOCEL"
}